Workbook

Sheet Início
B1: Caderninho — controle de fiado
B2: Planilha de custos, preços e fiado para qualquer negócio que vende para receber depois: cantina, lanchonete, doces e salgados, lojinha, revenda.
B4: Nome do negócio (se quiser)
B6: Na primeira vez, preencha nesta ordem:
B7: 1 | C7: Meu Mês | D7: Suas contas fixas, quanto você precisa para viver e quantas horas trabalha. A planilha calcula quanto vale a sua hora.
B8: 2 | C8: Materiais | D8: Se você prepara o que vende: tudo que compra para isso (ingredientes, embalagens), com o tamanho do pacote e o preço.
B9: 3 | C9: Produtos | D9: O que você vende. Se prepara: quanto a receita rende e quanto tempo leva. Se compra pronto: quanto paga por unidade.
B10: 4 | C10: Receitas | D10: Só para o que você prepara: o que vai e quanto vai. O preço sugerido aparece em Produtos.
B11: 5 | C11: Clientes | D11: Quem compra de você, com uma observação se quiser (turma, setor, responsável).
B13: No dia a dia:
B14: • | C14: Vendas | D14: Quem pegou o quê. Sem produto cadastrado? Escreva o que foi e o valor, como no caderno.
B15: • | C15: Recebi | D15: Quem te pagou, quanto e como (Pix, dinheiro, cartão).
B16: • | C16: Acertos | D16: Um presente, um desconto ou a correção do valor que alguém deve.
B17: • | C17: Resumo | D17: Quanto vendeu, quanto já recebeu, quem deve e se o mês pagou suas contas e o seu salário.
B19: As cores
C20: Azul clarinho | D20: Você preenche. Pode escrever por cima à vontade.
C21: Branco | D21: A planilha calcula sozinha. Não precisa mexer.
C22: Cinza | D22: Os números mais importantes.
C23: Vermelho | D23: Dívida, ou um preço que dá prejuízo.
C24: Verde | D24: Dinheiro que entrou e conta em dia.
B26: Como a planilha chega no preço
B27: 1 | C27: Custo da unidade | D27: Se prepara: materiais da receita, mais as perdas, divididos pelo rendimento. Se compra pronto: o que paga, mais as perdas.
B28: 2 | C28: Seu tempo e contas | D28: Só no que você prepara: horas da receita × quanto vale a sua hora, divididas pelo rendimento. É isso que paga as contas fixas e o seu salário.
B29: 3 | C29: Preço sugerido | D29: Custo completo, mais as taxas e o lucro que você quer. Arredondado para cima.
B30: 4 | C30: Como está | D30: Compara com o preço que você cobra hoje: Preço bom, Abaixo do sugerido, Não paga o seu tempo ou Prejuízo.
B32: Dicas
B33: • | C33: As linhas que já vêm preenchidas são exemplos. Escreva por cima ou apague.
B34: • | C34: Quilo vira gramas e litro vira ml: 1 kg = 1000 g, 1 litro = 1000 ml. Ovos, potes e peças são em unidades (un).
B35: • | C35: Mudou o preço de algo que você compra? Mude só na aba Materiais (ou em Produtos, se compra pronto): custos e preços sugeridos se atualizam sozinhos.
B36: • | C36: Na aba Vendas, escreva o preço que você cobrou. Assim, se mudar o preço depois, as vendas antigas não mudam.
B37: • | C37: Em breve o app Caderninho vai preencher esta planilha sozinho.

Sheet Resumo
B1: =IF(Negocio="","Resumo","Resumo · "&Negocio) -> Resumo
B2: Quanto você vendeu, quanto já entrou, quem está devendo e se o mês pagou as suas contas e o seu salário.
B4: Mês que quero ver | C4: =DATE(YEAR(TODAY()),MONTH(TODAY()),1) -> 46296 | D4: Começa no mês de hoje. Para ver outro, escreva a data (ex.: 01/09/2026).
B6: Dinheiro na rua
B7: Falta receber de todo mundo | C7: =SUMIF(Clientes!$H$5:$H$304,">0") -> 61.5 | D7: =COUNTIF(Clientes!$H$5:$H$304,">0.005")&" devendo" -> 3 devendo | E7: Veja quem na aba Clientes.
B9: Vendas
C10: Neste mês | D10: Desde o começo
B11: Vendi | C11: =SUMIFS(Vendas!$G$5:$G$3004,Vendas!$B$5:$B$3004,">="&$C$4,Vendas!$B$5:$B$3004,"<="&EOMONTH($C$4,0))+SUMIFS(Acertos!$D$5:$D$504,Acertos!$B$5:$B$504,">="&$C$4,Acertos!$B$5:$B$504,"<="&EOMONTH($C$4,0)) -> 190.5 | D11: =SUM(Vendas!$G$5:$G$3004)+SUM(Acertos!$D$5:$D$504) -> 190.5 | E11: Tudo que as pessoas pegaram, pago ou fiado, com descontos e acertos.
B12: Já recebi | C12: =SUMIFS(Recebi!$D$5:$D$3004,Recebi!$B$5:$B$3004,">="&$C$4,Recebi!$B$5:$B$3004,"<="&EOMONTH($C$4,0))+SUMIFS(Vendas!$G$5:$G$3004,Vendas!$J$5:$J$3004,"Sim",Vendas!$B$5:$B$3004,">="&$C$4,Vendas!$B$5:$B$3004,"<="&EOMONTH($C$4,0)) -> 129 | D12: =SUM(Recebi!$D$5:$D$3004)+SUMIFS(Vendas!$G$5:$G$3004,Vendas!$J$5:$J$3004,"Sim") -> 129 | E12: O dinheiro que já entrou.
B13: Gastei com materiais e mercadoria | C13: =SUMIFS(Vendas!$H$5:$H$3004,Vendas!$B$5:$B$3004,">="&$C$4,Vendas!$B$5:$B$3004,"<="&EOMONTH($C$4,0)) -> 66.445186 | D13: =SUM(Vendas!$H$5:$H$3004) -> 66.445186 | E13: Pelo custo de cada produto (aba Produtos).
B14: Taxas (maquininha, app) | C14: =C11*Taxas -> 5.715 | D14: =D11*Taxas -> 5.715 | E14: Uma estimativa, pela % da aba Meu Mês.
B15: Sobrou das vendas | C15: =C11-C13-C14 -> 118.33981 | D15: =D11-D13-D14 -> 118.33981 | E15: O que fica para pagar as contas e o seu salário.
B17: O mês pagou as contas e o seu salário?
B18: Contas fixas do mês | C18: =ContasFixas -> 407 | E18: Da aba Meu Mês.
B19: Ficou para mim | C19: =C15-C18 -> -288.66019 | E19: Sobrou das vendas menos as contas fixas (contando o fiado que ainda vai entrar).
B20: Meu salário | C20: =Salario -> 1500 | E20: O que você quer tirar por mês (aba Meu Mês).
B21: =IF(C11=0,"Ainda não tem vendas neste mês.",IF(C19>=C20,"Bateu o seu salário! E ainda sobrou "&"R$ "&FIXED(C19-C20,2)&" de lucro.",IF(C19>0,"Faltam "&"R$ "&FIXED(C20-C19,2)&" para chegar no seu salário.","As vendas ainda não pagaram as contas fixas do mês."))) -> As vendas ainda não pagaram as contas fixas do mês.
B23: Meta do mês
B24: De cada R$ 1,00 que vendo, sobra | C24: =IF(C11>0,(C11-C13)/C11-Taxas,IFERROR(AVERAGE(Produtos!$P$5:$P$104),0)) -> 0.62120637 | E24: Para pagar contas e salário. Quanto maior, melhor.
B25: Para pagar contas + salário, preciso vender | C25: =IF(C24>0,(ContasFixas+Salario)/C24,"") -> 3069.8333 | E25: Por mês.
B26: ="Para ter também "&TEXT(LucroDesejado,"0%")&" de lucro, preciso vender" -> Para ter também 15% de lucro, preciso vender | C26: =IF(C24-LucroDesejado>0,(ContasFixas+Salario)/(C24-LucroDesejado),"") -> 4047.059 | E26: =IF(C26="","Com os preços de hoje não dá esse lucro. Veja a aba Produtos.","Por mês.") -> Por mês.
B27: Já vendi da meta | C27: =IF(N(C25)=0,"",C11/C25) -> 0.062055487 | D27: =IF(C27="","",REPT("■",MIN(10,ROUND(C27*10,0)))&REPT("□",10-MIN(10,ROUND(C27*10,0)))) -> ■□□□□□□□□□ | E27: =IF(C27="","",IF(C11>=C25,"Meta batida!","Faltam "&"R$ "&FIXED(C25-C11,2)&" em vendas.")) -> Faltam R$ 2,879.33 em vendas.
B29: Por produto, neste mês
B30: Produto | C30: Unidades | D30: Vendi | E30: Sobrou
B31: =IF(Produtos!B5="","",Produtos!B5) -> Bolo de pote | C31: =IF(B31="","",SUMIFS(Vendas!$E$5:$E$3004,Vendas!$D$5:$D$3004,B31,Vendas!$B$5:$B$3004,">="&$C$4,Vendas!$B$5:$B$3004,"<="&EOMONTH($C$4,0))) -> 5 | D31: =IF(B31="","",SUMIFS(Vendas!$G$5:$G$3004,Vendas!$D$5:$D$3004,B31,Vendas!$B$5:$B$3004,">="&$C$4,Vendas!$B$5:$B$3004,"<="&EOMONTH($C$4,0))) -> 60 | E31: =IF(B31="","",SUMIFS(Vendas!$I$5:$I$3004,Vendas!$D$5:$D$3004,B31,Vendas!$B$5:$B$3004,">="&$C$4,Vendas!$B$5:$B$3004,"<="&EOMONTH($C$4,0))) -> 39.95884
B32: =IF(Produtos!B6="","",Produtos!B6) -> Coxinha de frango | C32: =IF(B32="","",SUMIFS(Vendas!$E$5:$E$3004,Vendas!$D$5:$D$3004,B32,Vendas!$B$5:$B$3004,">="&$C$4,Vendas!$B$5:$B$3004,"<="&EOMONTH($C$4,0))) -> 12 | D32: =IF(B32="","",SUMIFS(Vendas!$G$5:$G$3004,Vendas!$D$5:$D$3004,B32,Vendas!$B$5:$B$3004,">="&$C$4,Vendas!$B$5:$B$3004,"<="&EOMONTH($C$4,0))) -> 60 | E32: =IF(B32="","",SUMIFS(Vendas!$I$5:$I$3004,Vendas!$D$5:$D$3004,B32,Vendas!$B$5:$B$3004,">="&$C$4,Vendas!$B$5:$B$3004,"<="&EOMONTH($C$4,0))) -> 33.205774
B33: =IF(Produtos!B7="","",Produtos!B7) -> Brigadeiro | C33: =IF(B33="","",SUMIFS(Vendas!$E$5:$E$3004,Vendas!$D$5:$D$3004,B33,Vendas!$B$5:$B$3004,">="&$C$4,Vendas!$B$5:$B$3004,"<="&EOMONTH($C$4,0))) -> 20 | D33: =IF(B33="","",SUMIFS(Vendas!$G$5:$G$3004,Vendas!$D$5:$D$3004,B33,Vendas!$B$5:$B$3004,">="&$C$4,Vendas!$B$5:$B$3004,"<="&EOMONTH($C$4,0))) -> 50 | E33: =IF(B33="","",SUMIFS(Vendas!$I$5:$I$3004,Vendas!$D$5:$D$3004,B33,Vendas!$B$5:$B$3004,">="&$C$4,Vendas!$B$5:$B$3004,"<="&EOMONTH($C$4,0))) -> 40.4702
B34: =IF(Produtos!B8="","",Produtos!B8) -> Refrigerante lata | C34: =IF(B34="","",SUMIFS(Vendas!$E$5:$E$3004,Vendas!$D$5:$D$3004,B34,Vendas!$B$5:$B$3004,">="&$C$4,Vendas!$B$5:$B$3004,"<="&EOMONTH($C$4,0))) -> 3 | D34: =IF(B34="","",SUMIFS(Vendas!$G$5:$G$3004,Vendas!$D$5:$D$3004,B34,Vendas!$B$5:$B$3004,">="&$C$4,Vendas!$B$5:$B$3004,"<="&EOMONTH($C$4,0))) -> 18 | E34: =IF(B34="","",SUMIFS(Vendas!$I$5:$I$3004,Vendas!$D$5:$D$3004,B34,Vendas!$B$5:$B$3004,">="&$C$4,Vendas!$B$5:$B$3004,"<="&EOMONTH($C$4,0))) -> 7.92
B35: =IF(Produtos!B9="","",Produtos!B9) | C35: =IF(B35="","",SUMIFS(Vendas!$E$5:$E$3004,Vendas!$D$5:$D$3004,B35,Vendas!$B$5:$B$3004,">="&$C$4,Vendas!$B$5:$B$3004,"<="&EOMONTH($C$4,0))) | D35: =IF(B35="","",SUMIFS(Vendas!$G$5:$G$3004,Vendas!$D$5:$D$3004,B35,Vendas!$B$5:$B$3004,">="&$C$4,Vendas!$B$5:$B$3004,"<="&EOMONTH($C$4,0))) | E35: =IF(B35="","",SUMIFS(Vendas!$I$5:$I$3004,Vendas!$D$5:$D$3004,B35,Vendas!$B$5:$B$3004,">="&$C$4,Vendas!$B$5:$B$3004,"<="&EOMONTH($C$4,0)))
B36: =IF(Produtos!B10="","",Produtos!B10) | C36: =IF(B36="","",SUMIFS(Vendas!$E$5:$E$3004,Vendas!$D$5:$D$3004,B36,Vendas!$B$5:$B$3004,">="&$C$4,Vendas!$B$5:$B$3004,"<="&EOMONTH($C$4,0))) | D36: =IF(B36="","",SUMIFS(Vendas!$G$5:$G$3004,Vendas!$D$5:$D$3004,B36,Vendas!$B$5:$B$3004,">="&$C$4,Vendas!$B$5:$B$3004,"<="&EOMONTH($C$4,0))) | E36: =IF(B36="","",SUMIFS(Vendas!$I$5:$I$3004,Vendas!$D$5:$D$3004,B36,Vendas!$B$5:$B$3004,">="&$C$4,Vendas!$B$5:$B$3004,"<="&EOMONTH($C$4,0)))
B37: =IF(Produtos!B11="","",Produtos!B11) | C37: =IF(B37="","",SUMIFS(Vendas!$E$5:$E$3004,Vendas!$D$5:$D$3004,B37,Vendas!$B$5:$B$3004,">="&$C$4,Vendas!$B$5:$B$3004,"<="&EOMONTH($C$4,0))) | D37: =IF(B37="","",SUMIFS(Vendas!$G$5:$G$3004,Vendas!$D$5:$D$3004,B37,Vendas!$B$5:$B$3004,">="&$C$4,Vendas!$B$5:$B$3004,"<="&EOMONTH($C$4,0))) | E37: =IF(B37="","",SUMIFS(Vendas!$I$5:$I$3004,Vendas!$D$5:$D$3004,B37,Vendas!$B$5:$B$3004,">="&$C$4,Vendas!$B$5:$B$3004,"<="&EOMONTH($C$4,0)))
B38: =IF(Produtos!B12="","",Produtos!B12) | C38: =IF(B38="","",SUMIFS(Vendas!$E$5:$E$3004,Vendas!$D$5:$D$3004,B38,Vendas!$B$5:$B$3004,">="&$C$4,Vendas!$B$5:$B$3004,"<="&EOMONTH($C$4,0))) | D38: =IF(B38="","",SUMIFS(Vendas!$G$5:$G$3004,Vendas!$D$5:$D$3004,B38,Vendas!$B$5:$B$3004,">="&$C$4,Vendas!$B$5:$B$3004,"<="&EOMONTH($C$4,0))) | E38: =IF(B38="","",SUMIFS(Vendas!$I$5:$I$3004,Vendas!$D$5:$D$3004,B38,Vendas!$B$5:$B$3004,">="&$C$4,Vendas!$B$5:$B$3004,"<="&EOMONTH($C$4,0)))
B39: =IF(Produtos!B13="","",Produtos!B13) | C39: =IF(B39="","",SUMIFS(Vendas!$E$5:$E$3004,Vendas!$D$5:$D$3004,B39,Vendas!$B$5:$B$3004,">="&$C$4,Vendas!$B$5:$B$3004,"<="&EOMONTH($C$4,0))) | D39: =IF(B39="","",SUMIFS(Vendas!$G$5:$G$3004,Vendas!$D$5:$D$3004,B39,Vendas!$B$5:$B$3004,">="&$C$4,Vendas!$B$5:$B$3004,"<="&EOMONTH($C$4,0))) | E39: =IF(B39="","",SUMIFS(Vendas!$I$5:$I$3004,Vendas!$D$5:$D$3004,B39,Vendas!$B$5:$B$3004,">="&$C$4,Vendas!$B$5:$B$3004,"<="&EOMONTH($C$4,0)))
B40: =IF(Produtos!B14="","",Produtos!B14) | C40: =IF(B40="","",SUMIFS(Vendas!$E$5:$E$3004,Vendas!$D$5:$D$3004,B40,Vendas!$B$5:$B$3004,">="&$C$4,Vendas!$B$5:$B$3004,"<="&EOMONTH($C$4,0))) | D40: =IF(B40="","",SUMIFS(Vendas!$G$5:$G$3004,Vendas!$D$5:$D$3004,B40,Vendas!$B$5:$B$3004,">="&$C$4,Vendas!$B$5:$B$3004,"<="&EOMONTH($C$4,0))) | E40: =IF(B40="","",SUMIFS(Vendas!$I$5:$I$3004,Vendas!$D$5:$D$3004,B40,Vendas!$B$5:$B$3004,">="&$C$4,Vendas!$B$5:$B$3004,"<="&EOMONTH($C$4,0)))
B41: =IF(Produtos!B15="","",Produtos!B15) | C41: =IF(B41="","",SUMIFS(Vendas!$E$5:$E$3004,Vendas!$D$5:$D$3004,B41,Vendas!$B$5:$B$3004,">="&$C$4,Vendas!$B$5:$B$3004,"<="&EOMONTH($C$4,0))) | D41: =IF(B41="","",SUMIFS(Vendas!$G$5:$G$3004,Vendas!$D$5:$D$3004,B41,Vendas!$B$5:$B$3004,">="&$C$4,Vendas!$B$5:$B$3004,"<="&EOMONTH($C$4,0))) | E41: =IF(B41="","",SUMIFS(Vendas!$I$5:$I$3004,Vendas!$D$5:$D$3004,B41,Vendas!$B$5:$B$3004,">="&$C$4,Vendas!$B$5:$B$3004,"<="&EOMONTH($C$4,0)))
B42: =IF(Produtos!B16="","",Produtos!B16) | C42: =IF(B42="","",SUMIFS(Vendas!$E$5:$E$3004,Vendas!$D$5:$D$3004,B42,Vendas!$B$5:$B$3004,">="&$C$4,Vendas!$B$5:$B$3004,"<="&EOMONTH($C$4,0))) | D42: =IF(B42="","",SUMIFS(Vendas!$G$5:$G$3004,Vendas!$D$5:$D$3004,B42,Vendas!$B$5:$B$3004,">="&$C$4,Vendas!$B$5:$B$3004,"<="&EOMONTH($C$4,0))) | E42: =IF(B42="","",SUMIFS(Vendas!$I$5:$I$3004,Vendas!$D$5:$D$3004,B42,Vendas!$B$5:$B$3004,">="&$C$4,Vendas!$B$5:$B$3004,"<="&EOMONTH($C$4,0)))
... B130: =IF(Produtos!B104="","",Produtos!B104) | C130: =IF(B130="","",SUMIFS(Vendas!$E$5:$E$3004,Vendas!$D$5:$D$3004,B130,Vendas!$B$5:$B$3004,">="&$C$4,Vendas!$B$5:$B$3004,"<="&EOMONTH($C$4,0))) | D130: =IF(B130="","",SUMIFS(Vendas!$G$5:$G$3004,Vendas!$D$5:$D$3004,B130,Vendas!$B$5:$B$3004,">="&$C$4,Vendas!$B$5:$B$3004,"<="&EOMONTH($C$4,0))) | E130: =IF(B130="","",SUMIFS(Vendas!$I$5:$I$3004,Vendas!$D$5:$D$3004,B130,Vendas!$B$5:$B$3004,">="&$C$4,Vendas!$B$5:$B$3004,"<="&EOMONTH($C$4,0)))

Sheet Vendas
B1: Vendas
B2: Quem pegou o quê, uma linha por produto. Preço em branco usa o da aba Produtos. Sem produto cadastrado? Escreva o que foi e o valor, como no caderno.
B4: Data | C4: Cliente | D4: Produto (ou o que foi) | E4: Quantas | F4: Preço da unidade | G4: Total | H4: Custo | I4: Sobrou | J4: Pagou na hora?
B5: 46297 | C5: Ana | D5: Bolo de pote | E5: 2 | F5: 12 | G5: =IF(OR(C5="",AND(D5="",F5="")),"",IF(N(E5)=0,1,E5)*IF(F5="",IFERROR(N(INDEX(Produtos!$L$5:$L$104,MATCH(D5,Produtos!$B$5:$B$104,0))),0),F5)) -> 24 | H5: =IF(G5="","",IF(N(E5)=0,1,E5)*IFERROR(N(INDEX(Produtos!$G$5:$G$104,MATCH(D5,Produtos!$B$5:$B$104,0))),0)) -> 8.0164642 | I5: =IF(G5="","",G5-H5) -> 15.983536
B6: 46297 | C6: Bruno | D6: Brigadeiro | E6: 6 | F6: 2.5 | G6: =IF(OR(C6="",AND(D6="",F6="")),"",IF(N(E6)=0,1,E6)*IF(F6="",IFERROR(N(INDEX(Produtos!$L$5:$L$104,MATCH(D6,Produtos!$B$5:$B$104,0))),0),F6)) -> 15 | H6: =IF(G6="","",IF(N(E6)=0,1,E6)*IFERROR(N(INDEX(Produtos!$G$5:$G$104,MATCH(D6,Produtos!$B$5:$B$104,0))),0)) -> 2.85894 | I6: =IF(G6="","",G6-H6) -> 12.14106 | J6: Sim
B7: 46301 | C7: Carla | D7: Refrigerante lata | E7: 1 | F7: 6 | G7: =IF(OR(C7="",AND(D7="",F7="")),"",IF(N(E7)=0,1,E7)*IF(F7="",IFERROR(N(INDEX(Produtos!$L$5:$L$104,MATCH(D7,Produtos!$B$5:$B$104,0))),0),F7)) -> 6 | H7: =IF(G7="","",IF(N(E7)=0,1,E7)*IFERROR(N(INDEX(Produtos!$G$5:$G$104,MATCH(D7,Produtos!$B$5:$B$104,0))),0)) -> 3.36 | I7: =IF(G7="","",G7-H7) -> 2.64
B8: 46301 | C8: Carla | D8: Coxinha de frango | E8: 2 | F8: 5 | G8: =IF(OR(C8="",AND(D8="",F8="")),"",IF(N(E8)=0,1,E8)*IF(F8="",IFERROR(N(INDEX(Produtos!$L$5:$L$104,MATCH(D8,Produtos!$B$5:$B$104,0))),0),F8)) -> 10 | H8: =IF(G8="","",IF(N(E8)=0,1,E8)*IFERROR(N(INDEX(Produtos!$G$5:$G$104,MATCH(D8,Produtos!$B$5:$B$104,0))),0)) -> 4.4657042 | I8: =IF(G8="","",G8-H8) -> 5.5342958
B9: 46304 | C9: Lúcia | D9: Coxinha de frango | E9: 10 | F9: 5 | G9: =IF(OR(C9="",AND(D9="",F9="")),"",IF(N(E9)=0,1,E9)*IF(F9="",IFERROR(N(INDEX(Produtos!$L$5:$L$104,MATCH(D9,Produtos!$B$5:$B$104,0))),0),F9)) -> 50 | H9: =IF(G9="","",IF(N(E9)=0,1,E9)*IFERROR(N(INDEX(Produtos!$G$5:$G$104,MATCH(D9,Produtos!$B$5:$B$104,0))),0)) -> 22.328521 | I9: =IF(G9="","",G9-H9) -> 27.671479
B10: 46304 | C10: Lúcia | D10: Brigadeiro | E10: 10 | F10: 2.5 | G10: =IF(OR(C10="",AND(D10="",F10="")),"",IF(N(E10)=0,1,E10)*IF(F10="",IFERROR(N(INDEX(Produtos!$L$5:$L$104,MATCH(D10,Produtos!$B$5:$B$104,0))),0),F10)) -> 25 | H10: =IF(G10="","",IF(N(E10)=0,1,E10)*IFERROR(N(INDEX(Produtos!$G$5:$G$104,MATCH(D10,Produtos!$B$5:$B$104,0))),0)) -> 4.7649 | I10: =IF(G10="","",G10-H10) -> 20.2351
B11: 46309 | C11: Ana | D11: Lanche | E11: 1 | F11: 7.5 | G11: =IF(OR(C11="",AND(D11="",F11="")),"",IF(N(E11)=0,1,E11)*IF(F11="",IFERROR(N(INDEX(Produtos!$L$5:$L$104,MATCH(D11,Produtos!$B$5:$B$104,0))),0),F11)) -> 7.5 | H11: =IF(G11="","",IF(N(E11)=0,1,E11)*IFERROR(N(INDEX(Produtos!$G$5:$G$104,MATCH(D11,Produtos!$B$5:$B$104,0))),0)) -> 0 | I11: =IF(G11="","",G11-H11) -> 7.5
B12: 46311 | C12: João | D12: Bolo de pote | E12: 1 | F12: 12 | G12: =IF(OR(C12="",AND(D12="",F12="")),"",IF(N(E12)=0,1,E12)*IF(F12="",IFERROR(N(INDEX(Produtos!$L$5:$L$104,MATCH(D12,Produtos!$B$5:$B$104,0))),0),F12)) -> 12 | H12: =IF(G12="","",IF(N(E12)=0,1,E12)*IFERROR(N(INDEX(Produtos!$G$5:$G$104,MATCH(D12,Produtos!$B$5:$B$104,0))),0)) -> 4.0082321 | I12: =IF(G12="","",G12-H12) -> 7.9917679 | J12: Sim
B13: 46316 | C13: Carla | D13: Bolo de pote | E13: 2 | F13: 12 | G13: =IF(OR(C13="",AND(D13="",F13="")),"",IF(N(E13)=0,1,E13)*IF(F13="",IFERROR(N(INDEX(Produtos!$L$5:$L$104,MATCH(D13,Produtos!$B$5:$B$104,0))),0),F13)) -> 24 | H13: =IF(G13="","",IF(N(E13)=0,1,E13)*IFERROR(N(INDEX(Produtos!$G$5:$G$104,MATCH(D13,Produtos!$B$5:$B$104,0))),0)) -> 8.0164642 | I13: =IF(G13="","",G13-H13) -> 15.983536
B14: 46318 | C14: Bruno | D14: Refrigerante lata | E14: 2 | F14: 6 | G14: =IF(OR(C14="",AND(D14="",F14="")),"",IF(N(E14)=0,1,E14)*IF(F14="",IFERROR(N(INDEX(Produtos!$L$5:$L$104,MATCH(D14,Produtos!$B$5:$B$104,0))),0),F14)) -> 12 | H14: =IF(G14="","",IF(N(E14)=0,1,E14)*IFERROR(N(INDEX(Produtos!$G$5:$G$104,MATCH(D14,Produtos!$B$5:$B$104,0))),0)) -> 6.72 | I14: =IF(G14="","",G14-H14) -> 5.28
B15: 46323 | C15: Ana | D15: Brigadeiro | E15: 4 | F15: 2.5 | G15: =IF(OR(C15="",AND(D15="",F15="")),"",IF(N(E15)=0,1,E15)*IF(F15="",IFERROR(N(INDEX(Produtos!$L$5:$L$104,MATCH(D15,Produtos!$B$5:$B$104,0))),0),F15)) -> 10 | H15: =IF(G15="","",IF(N(E15)=0,1,E15)*IFERROR(N(INDEX(Produtos!$G$5:$G$104,MATCH(D15,Produtos!$B$5:$B$104,0))),0)) -> 1.90596 | I15: =IF(G15="","",G15-H15) -> 8.09404
G16: =IF(OR(C16="",AND(D16="",F16="")),"",IF(N(E16)=0,1,E16)*IF(F16="",IFERROR(N(INDEX(Produtos!$L$5:$L$104,MATCH(D16,Produtos!$B$5:$B$104,0))),0),F16)) | H16: =IF(G16="","",IF(N(E16)=0,1,E16)*IFERROR(N(INDEX(Produtos!$G$5:$G$104,MATCH(D16,Produtos!$B$5:$B$104,0))),0)) | I16: =IF(G16="","",G16-H16)
G17: =IF(OR(C17="",AND(D17="",F17="")),"",IF(N(E17)=0,1,E17)*IF(F17="",IFERROR(N(INDEX(Produtos!$L$5:$L$104,MATCH(D17,Produtos!$B$5:$B$104,0))),0),F17)) | H17: =IF(G17="","",IF(N(E17)=0,1,E17)*IFERROR(N(INDEX(Produtos!$G$5:$G$104,MATCH(D17,Produtos!$B$5:$B$104,0))),0)) | I17: =IF(G17="","",G17-H17)
G18: =IF(OR(C18="",AND(D18="",F18="")),"",IF(N(E18)=0,1,E18)*IF(F18="",IFERROR(N(INDEX(Produtos!$L$5:$L$104,MATCH(D18,Produtos!$B$5:$B$104,0))),0),F18)) | H18: =IF(G18="","",IF(N(E18)=0,1,E18)*IFERROR(N(INDEX(Produtos!$G$5:$G$104,MATCH(D18,Produtos!$B$5:$B$104,0))),0)) | I18: =IF(G18="","",G18-H18)
G19: =IF(OR(C19="",AND(D19="",F19="")),"",IF(N(E19)=0,1,E19)*IF(F19="",IFERROR(N(INDEX(Produtos!$L$5:$L$104,MATCH(D19,Produtos!$B$5:$B$104,0))),0),F19)) | H19: =IF(G19="","",IF(N(E19)=0,1,E19)*IFERROR(N(INDEX(Produtos!$G$5:$G$104,MATCH(D19,Produtos!$B$5:$B$104,0))),0)) | I19: =IF(G19="","",G19-H19)
G20: =IF(OR(C20="",AND(D20="",F20="")),"",IF(N(E20)=0,1,E20)*IF(F20="",IFERROR(N(INDEX(Produtos!$L$5:$L$104,MATCH(D20,Produtos!$B$5:$B$104,0))),0),F20)) | H20: =IF(G20="","",IF(N(E20)=0,1,E20)*IFERROR(N(INDEX(Produtos!$G$5:$G$104,MATCH(D20,Produtos!$B$5:$B$104,0))),0)) | I20: =IF(G20="","",G20-H20)
G21: =IF(OR(C21="",AND(D21="",F21="")),"",IF(N(E21)=0,1,E21)*IF(F21="",IFERROR(N(INDEX(Produtos!$L$5:$L$104,MATCH(D21,Produtos!$B$5:$B$104,0))),0),F21)) | H21: =IF(G21="","",IF(N(E21)=0,1,E21)*IFERROR(N(INDEX(Produtos!$G$5:$G$104,MATCH(D21,Produtos!$B$5:$B$104,0))),0)) | I21: =IF(G21="","",G21-H21)
G22: =IF(OR(C22="",AND(D22="",F22="")),"",IF(N(E22)=0,1,E22)*IF(F22="",IFERROR(N(INDEX(Produtos!$L$5:$L$104,MATCH(D22,Produtos!$B$5:$B$104,0))),0),F22)) | H22: =IF(G22="","",IF(N(E22)=0,1,E22)*IFERROR(N(INDEX(Produtos!$G$5:$G$104,MATCH(D22,Produtos!$B$5:$B$104,0))),0)) | I22: =IF(G22="","",G22-H22)
G23: =IF(OR(C23="",AND(D23="",F23="")),"",IF(N(E23)=0,1,E23)*IF(F23="",IFERROR(N(INDEX(Produtos!$L$5:$L$104,MATCH(D23,Produtos!$B$5:$B$104,0))),0),F23)) | H23: =IF(G23="","",IF(N(E23)=0,1,E23)*IFERROR(N(INDEX(Produtos!$G$5:$G$104,MATCH(D23,Produtos!$B$5:$B$104,0))),0)) | I23: =IF(G23="","",G23-H23)
G24: =IF(OR(C24="",AND(D24="",F24="")),"",IF(N(E24)=0,1,E24)*IF(F24="",IFERROR(N(INDEX(Produtos!$L$5:$L$104,MATCH(D24,Produtos!$B$5:$B$104,0))),0),F24)) | H24: =IF(G24="","",IF(N(E24)=0,1,E24)*IFERROR(N(INDEX(Produtos!$G$5:$G$104,MATCH(D24,Produtos!$B$5:$B$104,0))),0)) | I24: =IF(G24="","",G24-H24)
G25: =IF(OR(C25="",AND(D25="",F25="")),"",IF(N(E25)=0,1,E25)*IF(F25="",IFERROR(N(INDEX(Produtos!$L$5:$L$104,MATCH(D25,Produtos!$B$5:$B$104,0))),0),F25)) | H25: =IF(G25="","",IF(N(E25)=0,1,E25)*IFERROR(N(INDEX(Produtos!$G$5:$G$104,MATCH(D25,Produtos!$B$5:$B$104,0))),0)) | I25: =IF(G25="","",G25-H25)
G26: =IF(OR(C26="",AND(D26="",F26="")),"",IF(N(E26)=0,1,E26)*IF(F26="",IFERROR(N(INDEX(Produtos!$L$5:$L$104,MATCH(D26,Produtos!$B$5:$B$104,0))),0),F26)) | H26: =IF(G26="","",IF(N(E26)=0,1,E26)*IFERROR(N(INDEX(Produtos!$G$5:$G$104,MATCH(D26,Produtos!$B$5:$B$104,0))),0)) | I26: =IF(G26="","",G26-H26)
G27: =IF(OR(C27="",AND(D27="",F27="")),"",IF(N(E27)=0,1,E27)*IF(F27="",IFERROR(N(INDEX(Produtos!$L$5:$L$104,MATCH(D27,Produtos!$B$5:$B$104,0))),0),F27)) | H27: =IF(G27="","",IF(N(E27)=0,1,E27)*IFERROR(N(INDEX(Produtos!$G$5:$G$104,MATCH(D27,Produtos!$B$5:$B$104,0))),0)) | I27: =IF(G27="","",G27-H27)
... G3004: =IF(OR(C3004="",AND(D3004="",F3004="")),"",IF(N(E3004)=0,1,E3004)*IF(F3004="",IFERROR(N(INDEX(Produtos!$L$5:$L$104,MATCH(D3004,Produtos!$B$5:$B$104,0))),0),F3004)) | H3004: =IF(G3004="","",IF(N(E3004)=0,1,E3004)*IFERROR(N(INDEX(Produtos!$G$5:$G$104,MATCH(D3004,Produtos!$B$5:$B$104,0))),0)) | I3004: =IF(G3004="","",G3004-H3004)

Sheet Recebi
B1: Recebi
B2: Cada vez que alguém te pagar, uma linha aqui. Pode ser tudo ou só uma parte do que a pessoa deve.
B4: Data | C4: Cliente | D4: Quanto | E4: Como pagou | F4: Observação
B5: 46305 | C5: Ana | D5: 24 | E5: Pix
B6: 46310 | C6: Carla | D6: 16 | E6: Dinheiro
B7: 46315 | C7: Lúcia | D7: 50 | E7: Pix | F7: Pagou uma parte
B8: 46320 | C8: Bruno | D8: 12 | E8: Cartão

Sheet Acertos
B1: Descontos e acertos
B2: Para mudar o valor que alguém deve: um presente, um desconto ou a correção de um erro. Com menos (−) diminui o que a pessoa deve; sem sinal, aumenta.
B4: Data | C4: Cliente | D4: Valor (− diminui, + aumenta) | E4: Motivo | F4: Observação
B5: 46315 | C5: Lúcia | D5: -5 | E5: Presente | F5: Arredondei a conta

Sheet Clientes
B1: Clientes
B2: Quem compra de você. O quanto cada pessoa pegou, pagou e ainda deve aparece sozinho, pelas abas Vendas, Recebi e Acertos.
B4: Nome | C4: WhatsApp | D4: Observação (turma, setor, responsável) | E4: Já pegou | F4: Já pagou | G4: Descontos e acertos | H4: Está devendo | I4: Última compra | J4: Situação
B5: Ana | C5: (11) 90000-0001 | D5: RH | E5: =IF(B5="","",SUMIFS(Vendas!$G$5:$G$3004,Vendas!$C$5:$C$3004,B5)) -> 41.5 | F5: =IF(B5="","",SUMIFS(Recebi!$D$5:$D$3004,Recebi!$C$5:$C$3004,B5)+SUMIFS(Vendas!$G$5:$G$3004,Vendas!$C$5:$C$3004,B5,Vendas!$J$5:$J$3004,"Sim")) -> 24 | G5: =IF(B5="","",SUMIFS(Acertos!$D$5:$D$504,Acertos!$C$5:$C$504,B5)) -> 0 | H5: =IF(B5="","",E5+G5-F5) -> 17.5 | I5: =IF(B5="","",IF(COUNTIF(Vendas!$C$5:$C$3004,B5)=0,"",_xlfn.MAXIFS(Vendas!$B$5:$B$3004,Vendas!$C$5:$C$3004,B5))) -> 46323 | J5: =IF(B5="","",IF(H5>0.005,"Deve",IF(H5<-0.005,"Tem crédito",IF(E5>0,"Em dia","Ainda não comprou")))) -> Deve
B6: Bruno | C6: (11) 90000-0002 | D6: Portaria | E6: =IF(B6="","",SUMIFS(Vendas!$G$5:$G$3004,Vendas!$C$5:$C$3004,B6)) -> 27 | F6: =IF(B6="","",SUMIFS(Recebi!$D$5:$D$3004,Recebi!$C$5:$C$3004,B6)+SUMIFS(Vendas!$G$5:$G$3004,Vendas!$C$5:$C$3004,B6,Vendas!$J$5:$J$3004,"Sim")) -> 27 | G6: =IF(B6="","",SUMIFS(Acertos!$D$5:$D$504,Acertos!$C$5:$C$504,B6)) -> 0 | H6: =IF(B6="","",E6+G6-F6) -> 0 | I6: =IF(B6="","",IF(COUNTIF(Vendas!$C$5:$C$3004,B6)=0,"",_xlfn.MAXIFS(Vendas!$B$5:$B$3004,Vendas!$C$5:$C$3004,B6))) -> 46318 | J6: =IF(B6="","",IF(H6>0.005,"Deve",IF(H6<-0.005,"Tem crédito",IF(E6>0,"Em dia","Ainda não comprou")))) -> Em dia
B7: Carla | C7: (11) 90000-0003 | D7: 3º ano B | E7: =IF(B7="","",SUMIFS(Vendas!$G$5:$G$3004,Vendas!$C$5:$C$3004,B7)) -> 40 | F7: =IF(B7="","",SUMIFS(Recebi!$D$5:$D$3004,Recebi!$C$5:$C$3004,B7)+SUMIFS(Vendas!$G$5:$G$3004,Vendas!$C$5:$C$3004,B7,Vendas!$J$5:$J$3004,"Sim")) -> 16 | G7: =IF(B7="","",SUMIFS(Acertos!$D$5:$D$504,Acertos!$C$5:$C$504,B7)) -> 0 | H7: =IF(B7="","",E7+G7-F7) -> 24 | I7: =IF(B7="","",IF(COUNTIF(Vendas!$C$5:$C$3004,B7)=0,"",_xlfn.MAXIFS(Vendas!$B$5:$B$3004,Vendas!$C$5:$C$3004,B7))) -> 46316 | J7: =IF(B7="","",IF(H7>0.005,"Deve",IF(H7<-0.005,"Tem crédito",IF(E7>0,"Em dia","Ainda não comprou")))) -> Deve
B8: Lúcia | C8: (11) 90000-0004 | D8: Responsável pelo Pedro, 5º ano | E8: =IF(B8="","",SUMIFS(Vendas!$G$5:$G$3004,Vendas!$C$5:$C$3004,B8)) -> 75 | F8: =IF(B8="","",SUMIFS(Recebi!$D$5:$D$3004,Recebi!$C$5:$C$3004,B8)+SUMIFS(Vendas!$G$5:$G$3004,Vendas!$C$5:$C$3004,B8,Vendas!$J$5:$J$3004,"Sim")) -> 50 | G8: =IF(B8="","",SUMIFS(Acertos!$D$5:$D$504,Acertos!$C$5:$C$504,B8)) -> -5 | H8: =IF(B8="","",E8+G8-F8) -> 20 | I8: =IF(B8="","",IF(COUNTIF(Vendas!$C$5:$C$3004,B8)=0,"",_xlfn.MAXIFS(Vendas!$B$5:$B$3004,Vendas!$C$5:$C$3004,B8))) -> 46304 | J8: =IF(B8="","",IF(H8>0.005,"Deve",IF(H8<-0.005,"Tem crédito",IF(E8>0,"Em dia","Ainda não comprou")))) -> Deve
B9: João | C9: (11) 90000-0005 | D9: Vizinho | E9: =IF(B9="","",SUMIFS(Vendas!$G$5:$G$3004,Vendas!$C$5:$C$3004,B9)) -> 12 | F9: =IF(B9="","",SUMIFS(Recebi!$D$5:$D$3004,Recebi!$C$5:$C$3004,B9)+SUMIFS(Vendas!$G$5:$G$3004,Vendas!$C$5:$C$3004,B9,Vendas!$J$5:$J$3004,"Sim")) -> 12 | G9: =IF(B9="","",SUMIFS(Acertos!$D$5:$D$504,Acertos!$C$5:$C$504,B9)) -> 0 | H9: =IF(B9="","",E9+G9-F9) -> 0 | I9: =IF(B9="","",IF(COUNTIF(Vendas!$C$5:$C$3004,B9)=0,"",_xlfn.MAXIFS(Vendas!$B$5:$B$3004,Vendas!$C$5:$C$3004,B9))) -> 46311 | J9: =IF(B9="","",IF(H9>0.005,"Deve",IF(H9<-0.005,"Tem crédito",IF(E9>0,"Em dia","Ainda não comprou")))) -> Em dia
E10: =IF(B10="","",SUMIFS(Vendas!$G$5:$G$3004,Vendas!$C$5:$C$3004,B10)) | F10: =IF(B10="","",SUMIFS(Recebi!$D$5:$D$3004,Recebi!$C$5:$C$3004,B10)+SUMIFS(Vendas!$G$5:$G$3004,Vendas!$C$5:$C$3004,B10,Vendas!$J$5:$J$3004,"Sim")) | G10: =IF(B10="","",SUMIFS(Acertos!$D$5:$D$504,Acertos!$C$5:$C$504,B10)) | H10: =IF(B10="","",E10+G10-F10) | I10: =IF(B10="","",IF(COUNTIF(Vendas!$C$5:$C$3004,B10)=0,"",_xlfn.MAXIFS(Vendas!$B$5:$B$3004,Vendas!$C$5:$C$3004,B10))) | J10: =IF(B10="","",IF(H10>0.005,"Deve",IF(H10<-0.005,"Tem crédito",IF(E10>0,"Em dia","Ainda não comprou"))))
E11: =IF(B11="","",SUMIFS(Vendas!$G$5:$G$3004,Vendas!$C$5:$C$3004,B11)) | F11: =IF(B11="","",SUMIFS(Recebi!$D$5:$D$3004,Recebi!$C$5:$C$3004,B11)+SUMIFS(Vendas!$G$5:$G$3004,Vendas!$C$5:$C$3004,B11,Vendas!$J$5:$J$3004,"Sim")) | G11: =IF(B11="","",SUMIFS(Acertos!$D$5:$D$504,Acertos!$C$5:$C$504,B11)) | H11: =IF(B11="","",E11+G11-F11) | I11: =IF(B11="","",IF(COUNTIF(Vendas!$C$5:$C$3004,B11)=0,"",_xlfn.MAXIFS(Vendas!$B$5:$B$3004,Vendas!$C$5:$C$3004,B11))) | J11: =IF(B11="","",IF(H11>0.005,"Deve",IF(H11<-0.005,"Tem crédito",IF(E11>0,"Em dia","Ainda não comprou"))))
E12: =IF(B12="","",SUMIFS(Vendas!$G$5:$G$3004,Vendas!$C$5:$C$3004,B12)) | F12: =IF(B12="","",SUMIFS(Recebi!$D$5:$D$3004,Recebi!$C$5:$C$3004,B12)+SUMIFS(Vendas!$G$5:$G$3004,Vendas!$C$5:$C$3004,B12,Vendas!$J$5:$J$3004,"Sim")) | G12: =IF(B12="","",SUMIFS(Acertos!$D$5:$D$504,Acertos!$C$5:$C$504,B12)) | H12: =IF(B12="","",E12+G12-F12) | I12: =IF(B12="","",IF(COUNTIF(Vendas!$C$5:$C$3004,B12)=0,"",_xlfn.MAXIFS(Vendas!$B$5:$B$3004,Vendas!$C$5:$C$3004,B12))) | J12: =IF(B12="","",IF(H12>0.005,"Deve",IF(H12<-0.005,"Tem crédito",IF(E12>0,"Em dia","Ainda não comprou"))))
E13: =IF(B13="","",SUMIFS(Vendas!$G$5:$G$3004,Vendas!$C$5:$C$3004,B13)) | F13: =IF(B13="","",SUMIFS(Recebi!$D$5:$D$3004,Recebi!$C$5:$C$3004,B13)+SUMIFS(Vendas!$G$5:$G$3004,Vendas!$C$5:$C$3004,B13,Vendas!$J$5:$J$3004,"Sim")) | G13: =IF(B13="","",SUMIFS(Acertos!$D$5:$D$504,Acertos!$C$5:$C$504,B13)) | H13: =IF(B13="","",E13+G13-F13) | I13: =IF(B13="","",IF(COUNTIF(Vendas!$C$5:$C$3004,B13)=0,"",_xlfn.MAXIFS(Vendas!$B$5:$B$3004,Vendas!$C$5:$C$3004,B13))) | J13: =IF(B13="","",IF(H13>0.005,"Deve",IF(H13<-0.005,"Tem crédito",IF(E13>0,"Em dia","Ainda não comprou"))))
E14: =IF(B14="","",SUMIFS(Vendas!$G$5:$G$3004,Vendas!$C$5:$C$3004,B14)) | F14: =IF(B14="","",SUMIFS(Recebi!$D$5:$D$3004,Recebi!$C$5:$C$3004,B14)+SUMIFS(Vendas!$G$5:$G$3004,Vendas!$C$5:$C$3004,B14,Vendas!$J$5:$J$3004,"Sim")) | G14: =IF(B14="","",SUMIFS(Acertos!$D$5:$D$504,Acertos!$C$5:$C$504,B14)) | H14: =IF(B14="","",E14+G14-F14) | I14: =IF(B14="","",IF(COUNTIF(Vendas!$C$5:$C$3004,B14)=0,"",_xlfn.MAXIFS(Vendas!$B$5:$B$3004,Vendas!$C$5:$C$3004,B14))) | J14: =IF(B14="","",IF(H14>0.005,"Deve",IF(H14<-0.005,"Tem crédito",IF(E14>0,"Em dia","Ainda não comprou"))))
E15: =IF(B15="","",SUMIFS(Vendas!$G$5:$G$3004,Vendas!$C$5:$C$3004,B15)) | F15: =IF(B15="","",SUMIFS(Recebi!$D$5:$D$3004,Recebi!$C$5:$C$3004,B15)+SUMIFS(Vendas!$G$5:$G$3004,Vendas!$C$5:$C$3004,B15,Vendas!$J$5:$J$3004,"Sim")) | G15: =IF(B15="","",SUMIFS(Acertos!$D$5:$D$504,Acertos!$C$5:$C$504,B15)) | H15: =IF(B15="","",E15+G15-F15) | I15: =IF(B15="","",IF(COUNTIF(Vendas!$C$5:$C$3004,B15)=0,"",_xlfn.MAXIFS(Vendas!$B$5:$B$3004,Vendas!$C$5:$C$3004,B15))) | J15: =IF(B15="","",IF(H15>0.005,"Deve",IF(H15<-0.005,"Tem crédito",IF(E15>0,"Em dia","Ainda não comprou"))))
E16: =IF(B16="","",SUMIFS(Vendas!$G$5:$G$3004,Vendas!$C$5:$C$3004,B16)) | F16: =IF(B16="","",SUMIFS(Recebi!$D$5:$D$3004,Recebi!$C$5:$C$3004,B16)+SUMIFS(Vendas!$G$5:$G$3004,Vendas!$C$5:$C$3004,B16,Vendas!$J$5:$J$3004,"Sim")) | G16: =IF(B16="","",SUMIFS(Acertos!$D$5:$D$504,Acertos!$C$5:$C$504,B16)) | H16: =IF(B16="","",E16+G16-F16) | I16: =IF(B16="","",IF(COUNTIF(Vendas!$C$5:$C$3004,B16)=0,"",_xlfn.MAXIFS(Vendas!$B$5:$B$3004,Vendas!$C$5:$C$3004,B16))) | J16: =IF(B16="","",IF(H16>0.005,"Deve",IF(H16<-0.005,"Tem crédito",IF(E16>0,"Em dia","Ainda não comprou"))))
E17: =IF(B17="","",SUMIFS(Vendas!$G$5:$G$3004,Vendas!$C$5:$C$3004,B17)) | F17: =IF(B17="","",SUMIFS(Recebi!$D$5:$D$3004,Recebi!$C$5:$C$3004,B17)+SUMIFS(Vendas!$G$5:$G$3004,Vendas!$C$5:$C$3004,B17,Vendas!$J$5:$J$3004,"Sim")) | G17: =IF(B17="","",SUMIFS(Acertos!$D$5:$D$504,Acertos!$C$5:$C$504,B17)) | H17: =IF(B17="","",E17+G17-F17) | I17: =IF(B17="","",IF(COUNTIF(Vendas!$C$5:$C$3004,B17)=0,"",_xlfn.MAXIFS(Vendas!$B$5:$B$3004,Vendas!$C$5:$C$3004,B17))) | J17: =IF(B17="","",IF(H17>0.005,"Deve",IF(H17<-0.005,"Tem crédito",IF(E17>0,"Em dia","Ainda não comprou"))))
E18: =IF(B18="","",SUMIFS(Vendas!$G$5:$G$3004,Vendas!$C$5:$C$3004,B18)) | F18: =IF(B18="","",SUMIFS(Recebi!$D$5:$D$3004,Recebi!$C$5:$C$3004,B18)+SUMIFS(Vendas!$G$5:$G$3004,Vendas!$C$5:$C$3004,B18,Vendas!$J$5:$J$3004,"Sim")) | G18: =IF(B18="","",SUMIFS(Acertos!$D$5:$D$504,Acertos!$C$5:$C$504,B18)) | H18: =IF(B18="","",E18+G18-F18) | I18: =IF(B18="","",IF(COUNTIF(Vendas!$C$5:$C$3004,B18)=0,"",_xlfn.MAXIFS(Vendas!$B$5:$B$3004,Vendas!$C$5:$C$3004,B18))) | J18: =IF(B18="","",IF(H18>0.005,"Deve",IF(H18<-0.005,"Tem crédito",IF(E18>0,"Em dia","Ainda não comprou"))))
E19: =IF(B19="","",SUMIFS(Vendas!$G$5:$G$3004,Vendas!$C$5:$C$3004,B19)) | F19: =IF(B19="","",SUMIFS(Recebi!$D$5:$D$3004,Recebi!$C$5:$C$3004,B19)+SUMIFS(Vendas!$G$5:$G$3004,Vendas!$C$5:$C$3004,B19,Vendas!$J$5:$J$3004,"Sim")) | G19: =IF(B19="","",SUMIFS(Acertos!$D$5:$D$504,Acertos!$C$5:$C$504,B19)) | H19: =IF(B19="","",E19+G19-F19) | I19: =IF(B19="","",IF(COUNTIF(Vendas!$C$5:$C$3004,B19)=0,"",_xlfn.MAXIFS(Vendas!$B$5:$B$3004,Vendas!$C$5:$C$3004,B19))) | J19: =IF(B19="","",IF(H19>0.005,"Deve",IF(H19<-0.005,"Tem crédito",IF(E19>0,"Em dia","Ainda não comprou"))))
E20: =IF(B20="","",SUMIFS(Vendas!$G$5:$G$3004,Vendas!$C$5:$C$3004,B20)) | F20: =IF(B20="","",SUMIFS(Recebi!$D$5:$D$3004,Recebi!$C$5:$C$3004,B20)+SUMIFS(Vendas!$G$5:$G$3004,Vendas!$C$5:$C$3004,B20,Vendas!$J$5:$J$3004,"Sim")) | G20: =IF(B20="","",SUMIFS(Acertos!$D$5:$D$504,Acertos!$C$5:$C$504,B20)) | H20: =IF(B20="","",E20+G20-F20) | I20: =IF(B20="","",IF(COUNTIF(Vendas!$C$5:$C$3004,B20)=0,"",_xlfn.MAXIFS(Vendas!$B$5:$B$3004,Vendas!$C$5:$C$3004,B20))) | J20: =IF(B20="","",IF(H20>0.005,"Deve",IF(H20<-0.005,"Tem crédito",IF(E20>0,"Em dia","Ainda não comprou"))))
E21: =IF(B21="","",SUMIFS(Vendas!$G$5:$G$3004,Vendas!$C$5:$C$3004,B21)) | F21: =IF(B21="","",SUMIFS(Recebi!$D$5:$D$3004,Recebi!$C$5:$C$3004,B21)+SUMIFS(Vendas!$G$5:$G$3004,Vendas!$C$5:$C$3004,B21,Vendas!$J$5:$J$3004,"Sim")) | G21: =IF(B21="","",SUMIFS(Acertos!$D$5:$D$504,Acertos!$C$5:$C$504,B21)) | H21: =IF(B21="","",E21+G21-F21) | I21: =IF(B21="","",IF(COUNTIF(Vendas!$C$5:$C$3004,B21)=0,"",_xlfn.MAXIFS(Vendas!$B$5:$B$3004,Vendas!$C$5:$C$3004,B21))) | J21: =IF(B21="","",IF(H21>0.005,"Deve",IF(H21<-0.005,"Tem crédito",IF(E21>0,"Em dia","Ainda não comprou"))))
... E304: =IF(B304="","",SUMIFS(Vendas!$G$5:$G$3004,Vendas!$C$5:$C$3004,B304)) | F304: =IF(B304="","",SUMIFS(Recebi!$D$5:$D$3004,Recebi!$C$5:$C$3004,B304)+SUMIFS(Vendas!$G$5:$G$3004,Vendas!$C$5:$C$3004,B304,Vendas!$J$5:$J$3004,"Sim")) | G304: =IF(B304="","",SUMIFS(Acertos!$D$5:$D$504,Acertos!$C$5:$C$504,B304)) | H304: =IF(B304="","",E304+G304-F304) | I304: =IF(B304="","",IF(COUNTIF(Vendas!$C$5:$C$3004,B304)=0,"",_xlfn.MAXIFS(Vendas!$B$5:$B$3004,Vendas!$C$5:$C$3004,B304))) | J304: =IF(B304="","",IF(H304>0.005,"Deve",IF(H304<-0.005,"Tem crédito",IF(E304>0,"Em dia","Ainda não comprou"))))

Sheet Produtos
B1: Produtos e preços
B2: Quanto custa cada unidade e quanto cobrar. Se você prepara, preencha rendimento e tempo e monte a receita; se compra pronto para revender, preencha só quanto paga por unidade.
B4: Produto | C4: A receita rende (unidades) | D4: Tempo para fazer a receita (horas) | E4: Se compra pronto: quanto paga por unidade | F4: Materiais da receita | G4: Custo por unidade (materiais e perdas) | H4: Seu tempo e contas por unidade | I4: Custo completo por unidade | J4: Preço mínimo (sem prejuízo) | K4: Preço sugerido | L4: Preço que eu cobro | M4: Lucro por unidade | N4: Margem de lucro | O4: Como está
B5: Bolo de pote | C5: 12 | D5: 3 | F5: =IF(B5="","",SUMIFS(Receitas!$F$5:$F$504,Receitas!$B$5:$B$504,B5)) -> 45.808367 | G5: =IF(B5="","",IF(N(E5)>0,E5*(1+Perdas),IF(AND(N(C5)>0,N(F5)>0),F5*(1+Perdas)/C5,""))) -> 4.0082321 | H5: =IF(G5="","",IF(N(E5)>0,0,N(D5)*ValorHora/C5)) -> 4.3340909 | I5: =IF(G5="","",G5+H5) -> 8.342323 | J5: =IF(I5="","",I5/(1-Taxas)) -> 8.600333 | K5: =IF(I5="","",IF(Taxas+LucroDesejado>=1,"",IF(I5/(1-Taxas-LucroDesejado)<3,CEILING(I5/(1-Taxas-LucroDesejado),0.1),CEILING(I5/(1-Taxas-LucroDesejado),0.5)))) -> 10.5 | L5: 12 | M5: =IF(OR(I5="",N(L5)=0),"",L5-I5-L5*Taxas) -> 3.297677 | N5: =IF(M5="","",M5/L5) -> 0.27480642 | O5: =IF(B5="","",IF(AND(N(E5)=0,N(F5)=0),"Falta a receita ou o custo",IF(G5="","Falta o rendimento",IF(N(L5)=0,"Falta o seu preço",IF(L5<G5/(1-Taxas),"Prejuízo",IF(L5<J5-0.005,"Não paga o seu tempo",IF(L5<K5-0.005,"Abaixo do sugerido","Preço bom"))))))) -> Preço bom | P5: =IF(OR(G5="",N(L5)=0),"",(L5-G5)/L5-Taxas) -> 0.63598066
B6: Coxinha de frango | C6: 20 | D6: 3 | F6: =IF(B6="","",SUMIFS(Receitas!$F$5:$F$504,Receitas!$B$5:$B$504,B6)) -> 42.530517 | G6: =IF(B6="","",IF(N(E6)>0,E6*(1+Perdas),IF(AND(N(C6)>0,N(F6)>0),F6*(1+Perdas)/C6,""))) -> 2.2328521 | H6: =IF(G6="","",IF(N(E6)>0,0,N(D6)*ValorHora/C6)) -> 2.6004545 | I6: =IF(G6="","",G6+H6) -> 4.8333067 | J6: =IF(I6="","",I6/(1-Taxas)) -> 4.9827904 | K6: =IF(I6="","",IF(Taxas+LucroDesejado>=1,"",IF(I6/(1-Taxas-LucroDesejado)<3,CEILING(I6/(1-Taxas-LucroDesejado),0.1),CEILING(I6/(1-Taxas-LucroDesejado),0.5)))) -> 6 | L6: 5 | M6: =IF(OR(I6="",N(L6)=0),"",L6-I6-L6*Taxas) -> 0.01669333 | N6: =IF(M6="","",M6/L6) -> 0.0033386659 | O6: =IF(B6="","",IF(AND(N(E6)=0,N(F6)=0),"Falta a receita ou o custo",IF(G6="","Falta o rendimento",IF(N(L6)=0,"Falta o seu preço",IF(L6<G6/(1-Taxas),"Prejuízo",IF(L6<J6-0.005,"Não paga o seu tempo",IF(L6<K6-0.005,"Abaixo do sugerido","Preço bom"))))))) -> Abaixo do sugerido | P6: =IF(OR(G6="",N(L6)=0),"",(L6-G6)/L6-Taxas) -> 0.52342957
B7: Brigadeiro | C7: 30 | D7: 1.5 | F7: =IF(B7="","",SUMIFS(Receitas!$F$5:$F$504,Receitas!$B$5:$B$504,B7)) -> 13.614 | G7: =IF(B7="","",IF(N(E7)>0,E7*(1+Perdas),IF(AND(N(C7)>0,N(F7)>0),F7*(1+Perdas)/C7,""))) -> 0.47649 | H7: =IF(G7="","",IF(N(E7)>0,0,N(D7)*ValorHora/C7)) -> 0.86681818 | I7: =IF(G7="","",G7+H7) -> 1.3433082 | J7: =IF(I7="","",I7/(1-Taxas)) -> 1.3848538 | K7: =IF(I7="","",IF(Taxas+LucroDesejado>=1,"",IF(I7/(1-Taxas-LucroDesejado)<3,CEILING(I7/(1-Taxas-LucroDesejado),0.1),CEILING(I7/(1-Taxas-LucroDesejado),0.5)))) -> 1.7 | L7: 2.5 | M7: =IF(OR(I7="",N(L7)=0),"",L7-I7-L7*Taxas) -> 1.0816918 | N7: =IF(M7="","",M7/L7) -> 0.43267673 | O7: =IF(B7="","",IF(AND(N(E7)=0,N(F7)=0),"Falta a receita ou o custo",IF(G7="","Falta o rendimento",IF(N(L7)=0,"Falta o seu preço",IF(L7<G7/(1-Taxas),"Prejuízo",IF(L7<J7-0.005,"Não paga o seu tempo",IF(L7<K7-0.005,"Abaixo do sugerido","Preço bom"))))))) -> Preço bom | P7: =IF(OR(G7="",N(L7)=0),"",(L7-G7)/L7-Taxas) -> 0.779404
B8: Refrigerante lata | E8: 3.2 | F8: =IF(B8="","",SUMIFS(Receitas!$F$5:$F$504,Receitas!$B$5:$B$504,B8)) -> 0 | G8: =IF(B8="","",IF(N(E8)>0,E8*(1+Perdas),IF(AND(N(C8)>0,N(F8)>0),F8*(1+Perdas)/C8,""))) -> 3.36 | H8: =IF(G8="","",IF(N(E8)>0,0,N(D8)*ValorHora/C8)) -> 0 | I8: =IF(G8="","",G8+H8) -> 3.36 | J8: =IF(I8="","",I8/(1-Taxas)) -> 3.4639175 | K8: =IF(I8="","",IF(Taxas+LucroDesejado>=1,"",IF(I8/(1-Taxas-LucroDesejado)<3,CEILING(I8/(1-Taxas-LucroDesejado),0.1),CEILING(I8/(1-Taxas-LucroDesejado),0.5)))) -> 4.5 | L8: 6 | M8: =IF(OR(I8="",N(L8)=0),"",L8-I8-L8*Taxas) -> 2.46 | N8: =IF(M8="","",M8/L8) -> 0.41 | O8: =IF(B8="","",IF(AND(N(E8)=0,N(F8)=0),"Falta a receita ou o custo",IF(G8="","Falta o rendimento",IF(N(L8)=0,"Falta o seu preço",IF(L8<G8/(1-Taxas),"Prejuízo",IF(L8<J8-0.005,"Não paga o seu tempo",IF(L8<K8-0.005,"Abaixo do sugerido","Preço bom"))))))) -> Preço bom | P8: =IF(OR(G8="",N(L8)=0),"",(L8-G8)/L8-Taxas) -> 0.41
F9: =IF(B9="","",SUMIFS(Receitas!$F$5:$F$504,Receitas!$B$5:$B$504,B9)) | G9: =IF(B9="","",IF(N(E9)>0,E9*(1+Perdas),IF(AND(N(C9)>0,N(F9)>0),F9*(1+Perdas)/C9,""))) | H9: =IF(G9="","",IF(N(E9)>0,0,N(D9)*ValorHora/C9)) | I9: =IF(G9="","",G9+H9) | J9: =IF(I9="","",I9/(1-Taxas)) | K9: =IF(I9="","",IF(Taxas+LucroDesejado>=1,"",IF(I9/(1-Taxas-LucroDesejado)<3,CEILING(I9/(1-Taxas-LucroDesejado),0.1),CEILING(I9/(1-Taxas-LucroDesejado),0.5)))) | M9: =IF(OR(I9="",N(L9)=0),"",L9-I9-L9*Taxas) | N9: =IF(M9="","",M9/L9) | O9: =IF(B9="","",IF(AND(N(E9)=0,N(F9)=0),"Falta a receita ou o custo",IF(G9="","Falta o rendimento",IF(N(L9)=0,"Falta o seu preço",IF(L9<G9/(1-Taxas),"Prejuízo",IF(L9<J9-0.005,"Não paga o seu tempo",IF(L9<K9-0.005,"Abaixo do sugerido","Preço bom"))))))) | P9: =IF(OR(G9="",N(L9)=0),"",(L9-G9)/L9-Taxas)
F10: =IF(B10="","",SUMIFS(Receitas!$F$5:$F$504,Receitas!$B$5:$B$504,B10)) | G10: =IF(B10="","",IF(N(E10)>0,E10*(1+Perdas),IF(AND(N(C10)>0,N(F10)>0),F10*(1+Perdas)/C10,""))) | H10: =IF(G10="","",IF(N(E10)>0,0,N(D10)*ValorHora/C10)) | I10: =IF(G10="","",G10+H10) | J10: =IF(I10="","",I10/(1-Taxas)) | K10: =IF(I10="","",IF(Taxas+LucroDesejado>=1,"",IF(I10/(1-Taxas-LucroDesejado)<3,CEILING(I10/(1-Taxas-LucroDesejado),0.1),CEILING(I10/(1-Taxas-LucroDesejado),0.5)))) | M10: =IF(OR(I10="",N(L10)=0),"",L10-I10-L10*Taxas) | N10: =IF(M10="","",M10/L10) | O10: =IF(B10="","",IF(AND(N(E10)=0,N(F10)=0),"Falta a receita ou o custo",IF(G10="","Falta o rendimento",IF(N(L10)=0,"Falta o seu preço",IF(L10<G10/(1-Taxas),"Prejuízo",IF(L10<J10-0.005,"Não paga o seu tempo",IF(L10<K10-0.005,"Abaixo do sugerido","Preço bom"))))))) | P10: =IF(OR(G10="",N(L10)=0),"",(L10-G10)/L10-Taxas)
F11: =IF(B11="","",SUMIFS(Receitas!$F$5:$F$504,Receitas!$B$5:$B$504,B11)) | G11: =IF(B11="","",IF(N(E11)>0,E11*(1+Perdas),IF(AND(N(C11)>0,N(F11)>0),F11*(1+Perdas)/C11,""))) | H11: =IF(G11="","",IF(N(E11)>0,0,N(D11)*ValorHora/C11)) | I11: =IF(G11="","",G11+H11) | J11: =IF(I11="","",I11/(1-Taxas)) | K11: =IF(I11="","",IF(Taxas+LucroDesejado>=1,"",IF(I11/(1-Taxas-LucroDesejado)<3,CEILING(I11/(1-Taxas-LucroDesejado),0.1),CEILING(I11/(1-Taxas-LucroDesejado),0.5)))) | M11: =IF(OR(I11="",N(L11)=0),"",L11-I11-L11*Taxas) | N11: =IF(M11="","",M11/L11) | O11: =IF(B11="","",IF(AND(N(E11)=0,N(F11)=0),"Falta a receita ou o custo",IF(G11="","Falta o rendimento",IF(N(L11)=0,"Falta o seu preço",IF(L11<G11/(1-Taxas),"Prejuízo",IF(L11<J11-0.005,"Não paga o seu tempo",IF(L11<K11-0.005,"Abaixo do sugerido","Preço bom"))))))) | P11: =IF(OR(G11="",N(L11)=0),"",(L11-G11)/L11-Taxas)
F12: =IF(B12="","",SUMIFS(Receitas!$F$5:$F$504,Receitas!$B$5:$B$504,B12)) | G12: =IF(B12="","",IF(N(E12)>0,E12*(1+Perdas),IF(AND(N(C12)>0,N(F12)>0),F12*(1+Perdas)/C12,""))) | H12: =IF(G12="","",IF(N(E12)>0,0,N(D12)*ValorHora/C12)) | I12: =IF(G12="","",G12+H12) | J12: =IF(I12="","",I12/(1-Taxas)) | K12: =IF(I12="","",IF(Taxas+LucroDesejado>=1,"",IF(I12/(1-Taxas-LucroDesejado)<3,CEILING(I12/(1-Taxas-LucroDesejado),0.1),CEILING(I12/(1-Taxas-LucroDesejado),0.5)))) | M12: =IF(OR(I12="",N(L12)=0),"",L12-I12-L12*Taxas) | N12: =IF(M12="","",M12/L12) | O12: =IF(B12="","",IF(AND(N(E12)=0,N(F12)=0),"Falta a receita ou o custo",IF(G12="","Falta o rendimento",IF(N(L12)=0,"Falta o seu preço",IF(L12<G12/(1-Taxas),"Prejuízo",IF(L12<J12-0.005,"Não paga o seu tempo",IF(L12<K12-0.005,"Abaixo do sugerido","Preço bom"))))))) | P12: =IF(OR(G12="",N(L12)=0),"",(L12-G12)/L12-Taxas)
F13: =IF(B13="","",SUMIFS(Receitas!$F$5:$F$504,Receitas!$B$5:$B$504,B13)) | G13: =IF(B13="","",IF(N(E13)>0,E13*(1+Perdas),IF(AND(N(C13)>0,N(F13)>0),F13*(1+Perdas)/C13,""))) | H13: =IF(G13="","",IF(N(E13)>0,0,N(D13)*ValorHora/C13)) | I13: =IF(G13="","",G13+H13) | J13: =IF(I13="","",I13/(1-Taxas)) | K13: =IF(I13="","",IF(Taxas+LucroDesejado>=1,"",IF(I13/(1-Taxas-LucroDesejado)<3,CEILING(I13/(1-Taxas-LucroDesejado),0.1),CEILING(I13/(1-Taxas-LucroDesejado),0.5)))) | M13: =IF(OR(I13="",N(L13)=0),"",L13-I13-L13*Taxas) | N13: =IF(M13="","",M13/L13) | O13: =IF(B13="","",IF(AND(N(E13)=0,N(F13)=0),"Falta a receita ou o custo",IF(G13="","Falta o rendimento",IF(N(L13)=0,"Falta o seu preço",IF(L13<G13/(1-Taxas),"Prejuízo",IF(L13<J13-0.005,"Não paga o seu tempo",IF(L13<K13-0.005,"Abaixo do sugerido","Preço bom"))))))) | P13: =IF(OR(G13="",N(L13)=0),"",(L13-G13)/L13-Taxas)
F14: =IF(B14="","",SUMIFS(Receitas!$F$5:$F$504,Receitas!$B$5:$B$504,B14)) | G14: =IF(B14="","",IF(N(E14)>0,E14*(1+Perdas),IF(AND(N(C14)>0,N(F14)>0),F14*(1+Perdas)/C14,""))) | H14: =IF(G14="","",IF(N(E14)>0,0,N(D14)*ValorHora/C14)) | I14: =IF(G14="","",G14+H14) | J14: =IF(I14="","",I14/(1-Taxas)) | K14: =IF(I14="","",IF(Taxas+LucroDesejado>=1,"",IF(I14/(1-Taxas-LucroDesejado)<3,CEILING(I14/(1-Taxas-LucroDesejado),0.1),CEILING(I14/(1-Taxas-LucroDesejado),0.5)))) | M14: =IF(OR(I14="",N(L14)=0),"",L14-I14-L14*Taxas) | N14: =IF(M14="","",M14/L14) | O14: =IF(B14="","",IF(AND(N(E14)=0,N(F14)=0),"Falta a receita ou o custo",IF(G14="","Falta o rendimento",IF(N(L14)=0,"Falta o seu preço",IF(L14<G14/(1-Taxas),"Prejuízo",IF(L14<J14-0.005,"Não paga o seu tempo",IF(L14<K14-0.005,"Abaixo do sugerido","Preço bom"))))))) | P14: =IF(OR(G14="",N(L14)=0),"",(L14-G14)/L14-Taxas)
F15: =IF(B15="","",SUMIFS(Receitas!$F$5:$F$504,Receitas!$B$5:$B$504,B15)) | G15: =IF(B15="","",IF(N(E15)>0,E15*(1+Perdas),IF(AND(N(C15)>0,N(F15)>0),F15*(1+Perdas)/C15,""))) | H15: =IF(G15="","",IF(N(E15)>0,0,N(D15)*ValorHora/C15)) | I15: =IF(G15="","",G15+H15) | J15: =IF(I15="","",I15/(1-Taxas)) | K15: =IF(I15="","",IF(Taxas+LucroDesejado>=1,"",IF(I15/(1-Taxas-LucroDesejado)<3,CEILING(I15/(1-Taxas-LucroDesejado),0.1),CEILING(I15/(1-Taxas-LucroDesejado),0.5)))) | M15: =IF(OR(I15="",N(L15)=0),"",L15-I15-L15*Taxas) | N15: =IF(M15="","",M15/L15) | O15: =IF(B15="","",IF(AND(N(E15)=0,N(F15)=0),"Falta a receita ou o custo",IF(G15="","Falta o rendimento",IF(N(L15)=0,"Falta o seu preço",IF(L15<G15/(1-Taxas),"Prejuízo",IF(L15<J15-0.005,"Não paga o seu tempo",IF(L15<K15-0.005,"Abaixo do sugerido","Preço bom"))))))) | P15: =IF(OR(G15="",N(L15)=0),"",(L15-G15)/L15-Taxas)
F16: =IF(B16="","",SUMIFS(Receitas!$F$5:$F$504,Receitas!$B$5:$B$504,B16)) | G16: =IF(B16="","",IF(N(E16)>0,E16*(1+Perdas),IF(AND(N(C16)>0,N(F16)>0),F16*(1+Perdas)/C16,""))) | H16: =IF(G16="","",IF(N(E16)>0,0,N(D16)*ValorHora/C16)) | I16: =IF(G16="","",G16+H16) | J16: =IF(I16="","",I16/(1-Taxas)) | K16: =IF(I16="","",IF(Taxas+LucroDesejado>=1,"",IF(I16/(1-Taxas-LucroDesejado)<3,CEILING(I16/(1-Taxas-LucroDesejado),0.1),CEILING(I16/(1-Taxas-LucroDesejado),0.5)))) | M16: =IF(OR(I16="",N(L16)=0),"",L16-I16-L16*Taxas) | N16: =IF(M16="","",M16/L16) | O16: =IF(B16="","",IF(AND(N(E16)=0,N(F16)=0),"Falta a receita ou o custo",IF(G16="","Falta o rendimento",IF(N(L16)=0,"Falta o seu preço",IF(L16<G16/(1-Taxas),"Prejuízo",IF(L16<J16-0.005,"Não paga o seu tempo",IF(L16<K16-0.005,"Abaixo do sugerido","Preço bom"))))))) | P16: =IF(OR(G16="",N(L16)=0),"",(L16-G16)/L16-Taxas)
F17: =IF(B17="","",SUMIFS(Receitas!$F$5:$F$504,Receitas!$B$5:$B$504,B17)) | G17: =IF(B17="","",IF(N(E17)>0,E17*(1+Perdas),IF(AND(N(C17)>0,N(F17)>0),F17*(1+Perdas)/C17,""))) | H17: =IF(G17="","",IF(N(E17)>0,0,N(D17)*ValorHora/C17)) | I17: =IF(G17="","",G17+H17) | J17: =IF(I17="","",I17/(1-Taxas)) | K17: =IF(I17="","",IF(Taxas+LucroDesejado>=1,"",IF(I17/(1-Taxas-LucroDesejado)<3,CEILING(I17/(1-Taxas-LucroDesejado),0.1),CEILING(I17/(1-Taxas-LucroDesejado),0.5)))) | M17: =IF(OR(I17="",N(L17)=0),"",L17-I17-L17*Taxas) | N17: =IF(M17="","",M17/L17) | O17: =IF(B17="","",IF(AND(N(E17)=0,N(F17)=0),"Falta a receita ou o custo",IF(G17="","Falta o rendimento",IF(N(L17)=0,"Falta o seu preço",IF(L17<G17/(1-Taxas),"Prejuízo",IF(L17<J17-0.005,"Não paga o seu tempo",IF(L17<K17-0.005,"Abaixo do sugerido","Preço bom"))))))) | P17: =IF(OR(G17="",N(L17)=0),"",(L17-G17)/L17-Taxas)
F18: =IF(B18="","",SUMIFS(Receitas!$F$5:$F$504,Receitas!$B$5:$B$504,B18)) | G18: =IF(B18="","",IF(N(E18)>0,E18*(1+Perdas),IF(AND(N(C18)>0,N(F18)>0),F18*(1+Perdas)/C18,""))) | H18: =IF(G18="","",IF(N(E18)>0,0,N(D18)*ValorHora/C18)) | I18: =IF(G18="","",G18+H18) | J18: =IF(I18="","",I18/(1-Taxas)) | K18: =IF(I18="","",IF(Taxas+LucroDesejado>=1,"",IF(I18/(1-Taxas-LucroDesejado)<3,CEILING(I18/(1-Taxas-LucroDesejado),0.1),CEILING(I18/(1-Taxas-LucroDesejado),0.5)))) | M18: =IF(OR(I18="",N(L18)=0),"",L18-I18-L18*Taxas) | N18: =IF(M18="","",M18/L18) | O18: =IF(B18="","",IF(AND(N(E18)=0,N(F18)=0),"Falta a receita ou o custo",IF(G18="","Falta o rendimento",IF(N(L18)=0,"Falta o seu preço",IF(L18<G18/(1-Taxas),"Prejuízo",IF(L18<J18-0.005,"Não paga o seu tempo",IF(L18<K18-0.005,"Abaixo do sugerido","Preço bom"))))))) | P18: =IF(OR(G18="",N(L18)=0),"",(L18-G18)/L18-Taxas)
F19: =IF(B19="","",SUMIFS(Receitas!$F$5:$F$504,Receitas!$B$5:$B$504,B19)) | G19: =IF(B19="","",IF(N(E19)>0,E19*(1+Perdas),IF(AND(N(C19)>0,N(F19)>0),F19*(1+Perdas)/C19,""))) | H19: =IF(G19="","",IF(N(E19)>0,0,N(D19)*ValorHora/C19)) | I19: =IF(G19="","",G19+H19) | J19: =IF(I19="","",I19/(1-Taxas)) | K19: =IF(I19="","",IF(Taxas+LucroDesejado>=1,"",IF(I19/(1-Taxas-LucroDesejado)<3,CEILING(I19/(1-Taxas-LucroDesejado),0.1),CEILING(I19/(1-Taxas-LucroDesejado),0.5)))) | M19: =IF(OR(I19="",N(L19)=0),"",L19-I19-L19*Taxas) | N19: =IF(M19="","",M19/L19) | O19: =IF(B19="","",IF(AND(N(E19)=0,N(F19)=0),"Falta a receita ou o custo",IF(G19="","Falta o rendimento",IF(N(L19)=0,"Falta o seu preço",IF(L19<G19/(1-Taxas),"Prejuízo",IF(L19<J19-0.005,"Não paga o seu tempo",IF(L19<K19-0.005,"Abaixo do sugerido","Preço bom"))))))) | P19: =IF(OR(G19="",N(L19)=0),"",(L19-G19)/L19-Taxas)
F20: =IF(B20="","",SUMIFS(Receitas!$F$5:$F$504,Receitas!$B$5:$B$504,B20)) | G20: =IF(B20="","",IF(N(E20)>0,E20*(1+Perdas),IF(AND(N(C20)>0,N(F20)>0),F20*(1+Perdas)/C20,""))) | H20: =IF(G20="","",IF(N(E20)>0,0,N(D20)*ValorHora/C20)) | I20: =IF(G20="","",G20+H20) | J20: =IF(I20="","",I20/(1-Taxas)) | K20: =IF(I20="","",IF(Taxas+LucroDesejado>=1,"",IF(I20/(1-Taxas-LucroDesejado)<3,CEILING(I20/(1-Taxas-LucroDesejado),0.1),CEILING(I20/(1-Taxas-LucroDesejado),0.5)))) | M20: =IF(OR(I20="",N(L20)=0),"",L20-I20-L20*Taxas) | N20: =IF(M20="","",M20/L20) | O20: =IF(B20="","",IF(AND(N(E20)=0,N(F20)=0),"Falta a receita ou o custo",IF(G20="","Falta o rendimento",IF(N(L20)=0,"Falta o seu preço",IF(L20<G20/(1-Taxas),"Prejuízo",IF(L20<J20-0.005,"Não paga o seu tempo",IF(L20<K20-0.005,"Abaixo do sugerido","Preço bom"))))))) | P20: =IF(OR(G20="",N(L20)=0),"",(L20-G20)/L20-Taxas)
... F104: =IF(B104="","",SUMIFS(Receitas!$F$5:$F$504,Receitas!$B$5:$B$504,B104)) | G104: =IF(B104="","",IF(N(E104)>0,E104*(1+Perdas),IF(AND(N(C104)>0,N(F104)>0),F104*(1+Perdas)/C104,""))) | H104: =IF(G104="","",IF(N(E104)>0,0,N(D104)*ValorHora/C104)) | I104: =IF(G104="","",G104+H104) | J104: =IF(I104="","",I104/(1-Taxas)) | K104: =IF(I104="","",IF(Taxas+LucroDesejado>=1,"",IF(I104/(1-Taxas-LucroDesejado)<3,CEILING(I104/(1-Taxas-LucroDesejado),0.1),CEILING(I104/(1-Taxas-LucroDesejado),0.5)))) | M104: =IF(OR(I104="",N(L104)=0),"",L104-I104-L104*Taxas) | N104: =IF(M104="","",M104/L104) | O104: =IF(B104="","",IF(AND(N(E104)=0,N(F104)=0),"Falta a receita ou o custo",IF(G104="","Falta o rendimento",IF(N(L104)=0,"Falta o seu preço",IF(L104<G104/(1-Taxas),"Prejuízo",IF(L104<J104-0.005,"Não paga o seu tempo",IF(L104<K104-0.005,"Abaixo do sugerido","Preço bom"))))))) | P104: =IF(OR(G104="",N(L104)=0),"",(L104-G104)/L104-Taxas)

Sheet Receitas
B1: Receitas
B2: Só para o que você prepara: o que vai em cada produto e quanto vai, com as embalagens. Linhas do mesmo produto ficam juntas.
B4: Produto | C4: O que vai | D4: Quanto vai | E4: Medida | F4: Custo | G4: Observação
B5: Bolo de pote | C5: Farinha de trigo | D5: 240 | E5: =IF(C5="","",IFERROR(INDEX(Materiais!$D$5:$D$204,MATCH(C5,Materiais!$B$5:$B$204,0)),"?")) -> g | F5: =IF(OR(C5="",D5=""),"",IFERROR(D5*INDEX(Materiais!$F$5:$F$204,MATCH(C5,Materiais!$B$5:$B$204,0))/INDEX(Materiais!$E$5:$E$204,MATCH(C5,Materiais!$B$5:$B$204,0)),"Cadastre em Materiais")) -> 1.3176 | G5: massa
B6: Bolo de pote | C6: Açúcar refinado | D6: 300 | E6: =IF(C6="","",IFERROR(INDEX(Materiais!$D$5:$D$204,MATCH(C6,Materiais!$B$5:$B$204,0)),"?")) -> g | F6: =IF(OR(C6="",D6=""),"",IFERROR(D6*INDEX(Materiais!$F$5:$F$204,MATCH(C6,Materiais!$B$5:$B$204,0))/INDEX(Materiais!$E$5:$E$204,MATCH(C6,Materiais!$B$5:$B$204,0)),"Cadastre em Materiais")) -> 1.437 | G6: massa
B7: Bolo de pote | C7: Chocolate em pó 50% | D7: 100 | E7: =IF(C7="","",IFERROR(INDEX(Materiais!$D$5:$D$204,MATCH(C7,Materiais!$B$5:$B$204,0)),"?")) -> g | F7: =IF(OR(C7="",D7=""),"",IFERROR(D7*INDEX(Materiais!$F$5:$F$204,MATCH(C7,Materiais!$B$5:$B$204,0))/INDEX(Materiais!$E$5:$E$204,MATCH(C7,Materiais!$B$5:$B$204,0)),"Cadastre em Materiais")) -> 4.95 | G7: massa e recheio
B8: Bolo de pote | C8: Ovos | D8: 4 | E8: =IF(C8="","",IFERROR(INDEX(Materiais!$D$5:$D$204,MATCH(C8,Materiais!$B$5:$B$204,0)),"?")) -> un | F8: =IF(OR(C8="",D8=""),"",IFERROR(D8*INDEX(Materiais!$F$5:$F$204,MATCH(C8,Materiais!$B$5:$B$204,0))/INDEX(Materiais!$E$5:$E$204,MATCH(C8,Materiais!$B$5:$B$204,0)),"Cadastre em Materiais")) -> 2.6533333 | G8: massa
B9: Bolo de pote | C9: Leite | D9: 240 | E9: =IF(C9="","",IFERROR(INDEX(Materiais!$D$5:$D$204,MATCH(C9,Materiais!$B$5:$B$204,0)),"?")) -> ml | F9: =IF(OR(C9="",D9=""),"",IFERROR(D9*INDEX(Materiais!$F$5:$F$204,MATCH(C9,Materiais!$B$5:$B$204,0))/INDEX(Materiais!$E$5:$E$204,MATCH(C9,Materiais!$B$5:$B$204,0)),"Cadastre em Materiais")) -> 1.2696 | G9: massa
B10: Bolo de pote | C10: Óleo | D10: 120 | E10: =IF(C10="","",IFERROR(INDEX(Materiais!$D$5:$D$204,MATCH(C10,Materiais!$B$5:$B$204,0)),"?")) -> ml | F10: =IF(OR(C10="",D10=""),"",IFERROR(D10*INDEX(Materiais!$F$5:$F$204,MATCH(C10,Materiais!$B$5:$B$204,0))/INDEX(Materiais!$E$5:$E$204,MATCH(C10,Materiais!$B$5:$B$204,0)),"Cadastre em Materiais")) -> 1.0653333 | G10: massa
B11: Bolo de pote | C11: Fermento em pó | D11: 15 | E11: =IF(C11="","",IFERROR(INDEX(Materiais!$D$5:$D$204,MATCH(C11,Materiais!$B$5:$B$204,0)),"?")) -> g | F11: =IF(OR(C11="",D11=""),"",IFERROR(D11*INDEX(Materiais!$F$5:$F$204,MATCH(C11,Materiais!$B$5:$B$204,0))/INDEX(Materiais!$E$5:$E$204,MATCH(C11,Materiais!$B$5:$B$204,0)),"Cadastre em Materiais")) -> 0.5985 | G11: massa
B12: Bolo de pote | C12: Leite condensado | D12: 790 | E12: =IF(C12="","",IFERROR(INDEX(Materiais!$D$5:$D$204,MATCH(C12,Materiais!$B$5:$B$204,0)),"?")) -> g | F12: =IF(OR(C12="",D12=""),"",IFERROR(D12*INDEX(Materiais!$F$5:$F$204,MATCH(C12,Materiais!$B$5:$B$204,0))/INDEX(Materiais!$E$5:$E$204,MATCH(C12,Materiais!$B$5:$B$204,0)),"Cadastre em Materiais")) -> 12.98 | G12: recheio (2 latas)
B13: Bolo de pote | C13: Creme de leite | D13: 200 | E13: =IF(C13="","",IFERROR(INDEX(Materiais!$D$5:$D$204,MATCH(C13,Materiais!$B$5:$B$204,0)),"?")) -> g | F13: =IF(OR(C13="",D13=""),"",IFERROR(D13*INDEX(Materiais!$F$5:$F$204,MATCH(C13,Materiais!$B$5:$B$204,0))/INDEX(Materiais!$E$5:$E$204,MATCH(C13,Materiais!$B$5:$B$204,0)),"Cadastre em Materiais")) -> 3.29 | G13: recheio
B14: Bolo de pote | C14: Manteiga | D14: 30 | E14: =IF(C14="","",IFERROR(INDEX(Materiais!$D$5:$D$204,MATCH(C14,Materiais!$B$5:$B$204,0)),"?")) -> g | F14: =IF(OR(C14="",D14=""),"",IFERROR(D14*INDEX(Materiais!$F$5:$F$204,MATCH(C14,Materiais!$B$5:$B$204,0))/INDEX(Materiais!$E$5:$E$204,MATCH(C14,Materiais!$B$5:$B$204,0)),"Cadastre em Materiais")) -> 1.485 | G14: recheio
B15: Bolo de pote | C15: Chocolate granulado | D15: 50 | E15: =IF(C15="","",IFERROR(INDEX(Materiais!$D$5:$D$204,MATCH(C15,Materiais!$B$5:$B$204,0)),"?")) -> g | F15: =IF(OR(C15="",D15=""),"",IFERROR(D15*INDEX(Materiais!$F$5:$F$204,MATCH(C15,Materiais!$B$5:$B$204,0))/INDEX(Materiais!$E$5:$E$204,MATCH(C15,Materiais!$B$5:$B$204,0)),"Cadastre em Materiais")) -> 1.49 | G15: cobertura
B16: Bolo de pote | C16: Pote 250 ml com tampa | D16: 12 | E16: =IF(C16="","",IFERROR(INDEX(Materiais!$D$5:$D$204,MATCH(C16,Materiais!$B$5:$B$204,0)),"?")) -> un | F16: =IF(OR(C16="",D16=""),"",IFERROR(D16*INDEX(Materiais!$F$5:$F$204,MATCH(C16,Materiais!$B$5:$B$204,0))/INDEX(Materiais!$E$5:$E$204,MATCH(C16,Materiais!$B$5:$B$204,0)),"Cadastre em Materiais")) -> 9.576
B17: Bolo de pote | C17: Colher descartável | D17: 12 | E17: =IF(C17="","",IFERROR(INDEX(Materiais!$D$5:$D$204,MATCH(C17,Materiais!$B$5:$B$204,0)),"?")) -> un | F17: =IF(OR(C17="",D17=""),"",IFERROR(D17*INDEX(Materiais!$F$5:$F$204,MATCH(C17,Materiais!$B$5:$B$204,0))/INDEX(Materiais!$E$5:$E$204,MATCH(C17,Materiais!$B$5:$B$204,0)),"Cadastre em Materiais")) -> 1.896
B18: Bolo de pote | C18: Etiqueta com o nome do negócio | D18: 12 | E18: =IF(C18="","",IFERROR(INDEX(Materiais!$D$5:$D$204,MATCH(C18,Materiais!$B$5:$B$204,0)),"?")) -> un | F18: =IF(OR(C18="",D18=""),"",IFERROR(D18*INDEX(Materiais!$F$5:$F$204,MATCH(C18,Materiais!$B$5:$B$204,0))/INDEX(Materiais!$E$5:$E$204,MATCH(C18,Materiais!$B$5:$B$204,0)),"Cadastre em Materiais")) -> 1.8
B19: Coxinha de frango | C19: Peito de frango | D19: 800 | E19: =IF(C19="","",IFERROR(INDEX(Materiais!$D$5:$D$204,MATCH(C19,Materiais!$B$5:$B$204,0)),"?")) -> g | F19: =IF(OR(C19="",D19=""),"",IFERROR(D19*INDEX(Materiais!$F$5:$F$204,MATCH(C19,Materiais!$B$5:$B$204,0))/INDEX(Materiais!$E$5:$E$204,MATCH(C19,Materiais!$B$5:$B$204,0)),"Cadastre em Materiais")) -> 17.52 | G19: recheio
B20: Coxinha de frango | C20: Requeijão cremoso | D20: 200 | E20: =IF(C20="","",IFERROR(INDEX(Materiais!$D$5:$D$204,MATCH(C20,Materiais!$B$5:$B$204,0)),"?")) -> g | F20: =IF(OR(C20="",D20=""),"",IFERROR(D20*INDEX(Materiais!$F$5:$F$204,MATCH(C20,Materiais!$B$5:$B$204,0))/INDEX(Materiais!$E$5:$E$204,MATCH(C20,Materiais!$B$5:$B$204,0)),"Cadastre em Materiais")) -> 5.45 | G20: recheio
B21: Coxinha de frango | C21: Cebola | D21: 100 | E21: =IF(C21="","",IFERROR(INDEX(Materiais!$D$5:$D$204,MATCH(C21,Materiais!$B$5:$B$204,0)),"?")) -> g | F21: =IF(OR(C21="",D21=""),"",IFERROR(D21*INDEX(Materiais!$F$5:$F$204,MATCH(C21,Materiais!$B$5:$B$204,0))/INDEX(Materiais!$E$5:$E$204,MATCH(C21,Materiais!$B$5:$B$204,0)),"Cadastre em Materiais")) -> 0.599 | G21: recheio
B22: Coxinha de frango | C22: Farinha de trigo | D22: 500 | E22: =IF(C22="","",IFERROR(INDEX(Materiais!$D$5:$D$204,MATCH(C22,Materiais!$B$5:$B$204,0)),"?")) -> g | F22: =IF(OR(C22="",D22=""),"",IFERROR(D22*INDEX(Materiais!$F$5:$F$204,MATCH(C22,Materiais!$B$5:$B$204,0))/INDEX(Materiais!$E$5:$E$204,MATCH(C22,Materiais!$B$5:$B$204,0)),"Cadastre em Materiais")) -> 2.745 | G22: massa
B23: Coxinha de frango | C23: Leite | D23: 500 | E23: =IF(C23="","",IFERROR(INDEX(Materiais!$D$5:$D$204,MATCH(C23,Materiais!$B$5:$B$204,0)),"?")) -> ml | F23: =IF(OR(C23="",D23=""),"",IFERROR(D23*INDEX(Materiais!$F$5:$F$204,MATCH(C23,Materiais!$B$5:$B$204,0))/INDEX(Materiais!$E$5:$E$204,MATCH(C23,Materiais!$B$5:$B$204,0)),"Cadastre em Materiais")) -> 2.645 | G23: massa
B24: Coxinha de frango | C24: Manteiga | D24: 30 | E24: =IF(C24="","",IFERROR(INDEX(Materiais!$D$5:$D$204,MATCH(C24,Materiais!$B$5:$B$204,0)),"?")) -> g | F24: =IF(OR(C24="",D24=""),"",IFERROR(D24*INDEX(Materiais!$F$5:$F$204,MATCH(C24,Materiais!$B$5:$B$204,0))/INDEX(Materiais!$E$5:$E$204,MATCH(C24,Materiais!$B$5:$B$204,0)),"Cadastre em Materiais")) -> 1.485 | G24: massa
B25: Coxinha de frango | C25: Sal | D25: 15 | E25: =IF(C25="","",IFERROR(INDEX(Materiais!$D$5:$D$204,MATCH(C25,Materiais!$B$5:$B$204,0)),"?")) -> g | F25: =IF(OR(C25="",D25=""),"",IFERROR(D25*INDEX(Materiais!$F$5:$F$204,MATCH(C25,Materiais!$B$5:$B$204,0))/INDEX(Materiais!$E$5:$E$204,MATCH(C25,Materiais!$B$5:$B$204,0)),"Cadastre em Materiais")) -> 0.04485
B26: Coxinha de frango | C26: Ovos | D26: 2 | E26: =IF(C26="","",IFERROR(INDEX(Materiais!$D$5:$D$204,MATCH(C26,Materiais!$B$5:$B$204,0)),"?")) -> un | F26: =IF(OR(C26="",D26=""),"",IFERROR(D26*INDEX(Materiais!$F$5:$F$204,MATCH(C26,Materiais!$B$5:$B$204,0))/INDEX(Materiais!$E$5:$E$204,MATCH(C26,Materiais!$B$5:$B$204,0)),"Cadastre em Materiais")) -> 1.3266667 | G26: empanar
B27: Coxinha de frango | C27: Farinha de rosca | D27: 300 | E27: =IF(C27="","",IFERROR(INDEX(Materiais!$D$5:$D$204,MATCH(C27,Materiais!$B$5:$B$204,0)),"?")) -> g | F27: =IF(OR(C27="",D27=""),"",IFERROR(D27*INDEX(Materiais!$F$5:$F$204,MATCH(C27,Materiais!$B$5:$B$204,0))/INDEX(Materiais!$E$5:$E$204,MATCH(C27,Materiais!$B$5:$B$204,0)),"Cadastre em Materiais")) -> 4.14 | G27: empanar
B28: Coxinha de frango | C28: Óleo | D28: 450 | E28: =IF(C28="","",IFERROR(INDEX(Materiais!$D$5:$D$204,MATCH(C28,Materiais!$B$5:$B$204,0)),"?")) -> ml | F28: =IF(OR(C28="",D28=""),"",IFERROR(D28*INDEX(Materiais!$F$5:$F$204,MATCH(C28,Materiais!$B$5:$B$204,0))/INDEX(Materiais!$E$5:$E$204,MATCH(C28,Materiais!$B$5:$B$204,0)),"Cadastre em Materiais")) -> 3.995 | G28: fritura
B29: Coxinha de frango | C29: Caixa para salgado | D29: 2 | E29: =IF(C29="","",IFERROR(INDEX(Materiais!$D$5:$D$204,MATCH(C29,Materiais!$B$5:$B$204,0)),"?")) -> un | F29: =IF(OR(C29="",D29=""),"",IFERROR(D29*INDEX(Materiais!$F$5:$F$204,MATCH(C29,Materiais!$B$5:$B$204,0))/INDEX(Materiais!$E$5:$E$204,MATCH(C29,Materiais!$B$5:$B$204,0)),"Cadastre em Materiais")) -> 2.58
B30: Brigadeiro | C30: Leite condensado | D30: 395 | E30: =IF(C30="","",IFERROR(INDEX(Materiais!$D$5:$D$204,MATCH(C30,Materiais!$B$5:$B$204,0)),"?")) -> g | F30: =IF(OR(C30="",D30=""),"",IFERROR(D30*INDEX(Materiais!$F$5:$F$204,MATCH(C30,Materiais!$B$5:$B$204,0))/INDEX(Materiais!$E$5:$E$204,MATCH(C30,Materiais!$B$5:$B$204,0)),"Cadastre em Materiais")) -> 6.49
B31: Brigadeiro | C31: Chocolate em pó 50% | D31: 40 | E31: =IF(C31="","",IFERROR(INDEX(Materiais!$D$5:$D$204,MATCH(C31,Materiais!$B$5:$B$204,0)),"?")) -> g | F31: =IF(OR(C31="",D31=""),"",IFERROR(D31*INDEX(Materiais!$F$5:$F$204,MATCH(C31,Materiais!$B$5:$B$204,0))/INDEX(Materiais!$E$5:$E$204,MATCH(C31,Materiais!$B$5:$B$204,0)),"Cadastre em Materiais")) -> 1.98
B32: Brigadeiro | C32: Manteiga | D32: 20 | E32: =IF(C32="","",IFERROR(INDEX(Materiais!$D$5:$D$204,MATCH(C32,Materiais!$B$5:$B$204,0)),"?")) -> g | F32: =IF(OR(C32="",D32=""),"",IFERROR(D32*INDEX(Materiais!$F$5:$F$204,MATCH(C32,Materiais!$B$5:$B$204,0))/INDEX(Materiais!$E$5:$E$204,MATCH(C32,Materiais!$B$5:$B$204,0)),"Cadastre em Materiais")) -> 0.99
B33: Brigadeiro | C33: Chocolate granulado | D33: 80 | E33: =IF(C33="","",IFERROR(INDEX(Materiais!$D$5:$D$204,MATCH(C33,Materiais!$B$5:$B$204,0)),"?")) -> g | F33: =IF(OR(C33="",D33=""),"",IFERROR(D33*INDEX(Materiais!$F$5:$F$204,MATCH(C33,Materiais!$B$5:$B$204,0))/INDEX(Materiais!$E$5:$E$204,MATCH(C33,Materiais!$B$5:$B$204,0)),"Cadastre em Materiais")) -> 2.384
B34: Brigadeiro | C34: Forminha nº 4 | D34: 30 | E34: =IF(C34="","",IFERROR(INDEX(Materiais!$D$5:$D$204,MATCH(C34,Materiais!$B$5:$B$204,0)),"?")) -> un | F34: =IF(OR(C34="",D34=""),"",IFERROR(D34*INDEX(Materiais!$F$5:$F$204,MATCH(C34,Materiais!$B$5:$B$204,0))/INDEX(Materiais!$E$5:$E$204,MATCH(C34,Materiais!$B$5:$B$204,0)),"Cadastre em Materiais")) -> 1.77
E35: =IF(C35="","",IFERROR(INDEX(Materiais!$D$5:$D$204,MATCH(C35,Materiais!$B$5:$B$204,0)),"?")) | F35: =IF(OR(C35="",D35=""),"",IFERROR(D35*INDEX(Materiais!$F$5:$F$204,MATCH(C35,Materiais!$B$5:$B$204,0))/INDEX(Materiais!$E$5:$E$204,MATCH(C35,Materiais!$B$5:$B$204,0)),"Cadastre em Materiais"))
E36: =IF(C36="","",IFERROR(INDEX(Materiais!$D$5:$D$204,MATCH(C36,Materiais!$B$5:$B$204,0)),"?")) | F36: =IF(OR(C36="",D36=""),"",IFERROR(D36*INDEX(Materiais!$F$5:$F$204,MATCH(C36,Materiais!$B$5:$B$204,0))/INDEX(Materiais!$E$5:$E$204,MATCH(C36,Materiais!$B$5:$B$204,0)),"Cadastre em Materiais"))
E37: =IF(C37="","",IFERROR(INDEX(Materiais!$D$5:$D$204,MATCH(C37,Materiais!$B$5:$B$204,0)),"?")) | F37: =IF(OR(C37="",D37=""),"",IFERROR(D37*INDEX(Materiais!$F$5:$F$204,MATCH(C37,Materiais!$B$5:$B$204,0))/INDEX(Materiais!$E$5:$E$204,MATCH(C37,Materiais!$B$5:$B$204,0)),"Cadastre em Materiais"))
E38: =IF(C38="","",IFERROR(INDEX(Materiais!$D$5:$D$204,MATCH(C38,Materiais!$B$5:$B$204,0)),"?")) | F38: =IF(OR(C38="",D38=""),"",IFERROR(D38*INDEX(Materiais!$F$5:$F$204,MATCH(C38,Materiais!$B$5:$B$204,0))/INDEX(Materiais!$E$5:$E$204,MATCH(C38,Materiais!$B$5:$B$204,0)),"Cadastre em Materiais"))
E39: =IF(C39="","",IFERROR(INDEX(Materiais!$D$5:$D$204,MATCH(C39,Materiais!$B$5:$B$204,0)),"?")) | F39: =IF(OR(C39="",D39=""),"",IFERROR(D39*INDEX(Materiais!$F$5:$F$204,MATCH(C39,Materiais!$B$5:$B$204,0))/INDEX(Materiais!$E$5:$E$204,MATCH(C39,Materiais!$B$5:$B$204,0)),"Cadastre em Materiais"))
E40: =IF(C40="","",IFERROR(INDEX(Materiais!$D$5:$D$204,MATCH(C40,Materiais!$B$5:$B$204,0)),"?")) | F40: =IF(OR(C40="",D40=""),"",IFERROR(D40*INDEX(Materiais!$F$5:$F$204,MATCH(C40,Materiais!$B$5:$B$204,0))/INDEX(Materiais!$E$5:$E$204,MATCH(C40,Materiais!$B$5:$B$204,0)),"Cadastre em Materiais"))
E41: =IF(C41="","",IFERROR(INDEX(Materiais!$D$5:$D$204,MATCH(C41,Materiais!$B$5:$B$204,0)),"?")) | F41: =IF(OR(C41="",D41=""),"",IFERROR(D41*INDEX(Materiais!$F$5:$F$204,MATCH(C41,Materiais!$B$5:$B$204,0))/INDEX(Materiais!$E$5:$E$204,MATCH(C41,Materiais!$B$5:$B$204,0)),"Cadastre em Materiais"))
E42: =IF(C42="","",IFERROR(INDEX(Materiais!$D$5:$D$204,MATCH(C42,Materiais!$B$5:$B$204,0)),"?")) | F42: =IF(OR(C42="",D42=""),"",IFERROR(D42*INDEX(Materiais!$F$5:$F$204,MATCH(C42,Materiais!$B$5:$B$204,0))/INDEX(Materiais!$E$5:$E$204,MATCH(C42,Materiais!$B$5:$B$204,0)),"Cadastre em Materiais"))
E43: =IF(C43="","",IFERROR(INDEX(Materiais!$D$5:$D$204,MATCH(C43,Materiais!$B$5:$B$204,0)),"?")) | F43: =IF(OR(C43="",D43=""),"",IFERROR(D43*INDEX(Materiais!$F$5:$F$204,MATCH(C43,Materiais!$B$5:$B$204,0))/INDEX(Materiais!$E$5:$E$204,MATCH(C43,Materiais!$B$5:$B$204,0)),"Cadastre em Materiais"))
E44: =IF(C44="","",IFERROR(INDEX(Materiais!$D$5:$D$204,MATCH(C44,Materiais!$B$5:$B$204,0)),"?")) | F44: =IF(OR(C44="",D44=""),"",IFERROR(D44*INDEX(Materiais!$F$5:$F$204,MATCH(C44,Materiais!$B$5:$B$204,0))/INDEX(Materiais!$E$5:$E$204,MATCH(C44,Materiais!$B$5:$B$204,0)),"Cadastre em Materiais"))
E45: =IF(C45="","",IFERROR(INDEX(Materiais!$D$5:$D$204,MATCH(C45,Materiais!$B$5:$B$204,0)),"?")) | F45: =IF(OR(C45="",D45=""),"",IFERROR(D45*INDEX(Materiais!$F$5:$F$204,MATCH(C45,Materiais!$B$5:$B$204,0))/INDEX(Materiais!$E$5:$E$204,MATCH(C45,Materiais!$B$5:$B$204,0)),"Cadastre em Materiais"))
E46: =IF(C46="","",IFERROR(INDEX(Materiais!$D$5:$D$204,MATCH(C46,Materiais!$B$5:$B$204,0)),"?")) | F46: =IF(OR(C46="",D46=""),"",IFERROR(D46*INDEX(Materiais!$F$5:$F$204,MATCH(C46,Materiais!$B$5:$B$204,0))/INDEX(Materiais!$E$5:$E$204,MATCH(C46,Materiais!$B$5:$B$204,0)),"Cadastre em Materiais"))
... E504: =IF(C504="","",IFERROR(INDEX(Materiais!$D$5:$D$204,MATCH(C504,Materiais!$B$5:$B$204,0)),"?")) | F504: =IF(OR(C504="",D504=""),"",IFERROR(D504*INDEX(Materiais!$F$5:$F$204,MATCH(C504,Materiais!$B$5:$B$204,0))/INDEX(Materiais!$E$5:$E$204,MATCH(C504,Materiais!$B$5:$B$204,0)),"Cadastre em Materiais"))

Sheet Materiais
B1: Materiais
B2: Tudo que você compra para preparar o que vende: ingredientes, embalagens, materiais. Quilo vira gramas (1 kg = 1000 g) e litro vira ml (1 L = 1000 ml).
B4: O que é | C4: Tipo | D4: Medida (g, ml ou un) | E4: Quanto vem no pacote | F4: Quanto paguei | G4: Sai por | I4: Onde comprei | J4: Atualizado em
B5: Leite condensado | C5: Ingrediente | D5: g | E5: 395 | F5: 6.49 | G5: =IF(OR(B5="",E5="",F5="",N(E5)=0),"",IF(OR(D5="g",D5="ml"),F5/E5*1000,F5/E5)) -> 16.43038 | H5: =IF(G5="","",IF(D5="g","o quilo",IF(D5="ml","o litro","a unidade"))) -> o quilo | I5: Mercado | J5: 46325
B6: Creme de leite | C6: Ingrediente | D6: g | E6: 200 | F6: 3.29 | G6: =IF(OR(B6="",E6="",F6="",N(E6)=0),"",IF(OR(D6="g",D6="ml"),F6/E6*1000,F6/E6)) -> 16.45 | H6: =IF(G6="","",IF(D6="g","o quilo",IF(D6="ml","o litro","a unidade"))) -> o quilo | I6: Mercado | J6: 46325
B7: Chocolate em pó 50% | C7: Ingrediente | D7: g | E7: 200 | F7: 9.9 | G7: =IF(OR(B7="",E7="",F7="",N(E7)=0),"",IF(OR(D7="g",D7="ml"),F7/E7*1000,F7/E7)) -> 49.5 | H7: =IF(G7="","",IF(D7="g","o quilo",IF(D7="ml","o litro","a unidade"))) -> o quilo | I7: Mercado | J7: 46325
B8: Chocolate granulado | C8: Ingrediente | D8: g | E8: 500 | F8: 14.9 | G8: =IF(OR(B8="",E8="",F8="",N(E8)=0),"",IF(OR(D8="g",D8="ml"),F8/E8*1000,F8/E8)) -> 29.8 | H8: =IF(G8="","",IF(D8="g","o quilo",IF(D8="ml","o litro","a unidade"))) -> o quilo | I8: Atacado | J8: 46325
B9: Manteiga | C9: Ingrediente | D9: g | E9: 200 | F9: 9.9 | G9: =IF(OR(B9="",E9="",F9="",N(E9)=0),"",IF(OR(D9="g",D9="ml"),F9/E9*1000,F9/E9)) -> 49.5 | H9: =IF(G9="","",IF(D9="g","o quilo",IF(D9="ml","o litro","a unidade"))) -> o quilo | I9: Mercado | J9: 46325
B10: Açúcar refinado | C10: Ingrediente | D10: g | E10: 1000 | F10: 4.79 | G10: =IF(OR(B10="",E10="",F10="",N(E10)=0),"",IF(OR(D10="g",D10="ml"),F10/E10*1000,F10/E10)) -> 4.79 | H10: =IF(G10="","",IF(D10="g","o quilo",IF(D10="ml","o litro","a unidade"))) -> o quilo | I10: Mercado | J10: 46325
B11: Farinha de trigo | C11: Ingrediente | D11: g | E11: 1000 | F11: 5.49 | G11: =IF(OR(B11="",E11="",F11="",N(E11)=0),"",IF(OR(D11="g",D11="ml"),F11/E11*1000,F11/E11)) -> 5.49 | H11: =IF(G11="","",IF(D11="g","o quilo",IF(D11="ml","o litro","a unidade"))) -> o quilo | I11: Mercado | J11: 46325
B12: Ovos | C12: Ingrediente | D12: un | E12: 30 | F12: 19.9 | G12: =IF(OR(B12="",E12="",F12="",N(E12)=0),"",IF(OR(D12="g",D12="ml"),F12/E12*1000,F12/E12)) -> 0.66333333 | H12: =IF(G12="","",IF(D12="g","o quilo",IF(D12="ml","o litro","a unidade"))) -> a unidade | I12: Feira | J12: 46325
B13: Leite | C13: Ingrediente | D13: ml | E13: 1000 | F13: 5.29 | G13: =IF(OR(B13="",E13="",F13="",N(E13)=0),"",IF(OR(D13="g",D13="ml"),F13/E13*1000,F13/E13)) -> 5.29 | H13: =IF(G13="","",IF(D13="g","o quilo",IF(D13="ml","o litro","a unidade"))) -> o litro | I13: Mercado | J13: 46325
B14: Óleo | C14: Ingrediente | D14: ml | E14: 900 | F14: 7.99 | G14: =IF(OR(B14="",E14="",F14="",N(E14)=0),"",IF(OR(D14="g",D14="ml"),F14/E14*1000,F14/E14)) -> 8.8777778 | H14: =IF(G14="","",IF(D14="g","o quilo",IF(D14="ml","o litro","a unidade"))) -> o litro | I14: Mercado | J14: 46325
B15: Fermento em pó | C15: Ingrediente | D15: g | E15: 100 | F15: 3.99 | G15: =IF(OR(B15="",E15="",F15="",N(E15)=0),"",IF(OR(D15="g",D15="ml"),F15/E15*1000,F15/E15)) -> 39.9 | H15: =IF(G15="","",IF(D15="g","o quilo",IF(D15="ml","o litro","a unidade"))) -> o quilo | I15: Mercado | J15: 46325
B16: Peito de frango | C16: Ingrediente | D16: g | E16: 1000 | F16: 21.9 | G16: =IF(OR(B16="",E16="",F16="",N(E16)=0),"",IF(OR(D16="g",D16="ml"),F16/E16*1000,F16/E16)) -> 21.9 | H16: =IF(G16="","",IF(D16="g","o quilo",IF(D16="ml","o litro","a unidade"))) -> o quilo | I16: Açougue | J16: 46325
... B25: Caixa para salgado | C25: Embalagem | D25: un | E25: 10 | F25: 12.9 | G25: =IF(OR(B25="",E25="",F25="",N(E25)=0),"",IF(OR(D25="g",D25="ml"),F25/E25*1000,F25/E25)) -> 1.29 | H25: =IF(G25="","",IF(D25="g","o quilo",IF(D25="ml","o litro","a unidade"))) -> a unidade | I25: Loja de embalagem | J25: 46325
G26: =IF(OR(B26="",E26="",F26="",N(E26)=0),"",IF(OR(D26="g",D26="ml"),F26/E26*1000,F26/E26)) | H26: =IF(G26="","",IF(D26="g","o quilo",IF(D26="ml","o litro","a unidade")))
G27: =IF(OR(B27="",E27="",F27="",N(E27)=0),"",IF(OR(D27="g",D27="ml"),F27/E27*1000,F27/E27)) | H27: =IF(G27="","",IF(D27="g","o quilo",IF(D27="ml","o litro","a unidade")))
G28: =IF(OR(B28="",E28="",F28="",N(E28)=0),"",IF(OR(D28="g",D28="ml"),F28/E28*1000,F28/E28)) | H28: =IF(G28="","",IF(D28="g","o quilo",IF(D28="ml","o litro","a unidade")))
G29: =IF(OR(B29="",E29="",F29="",N(E29)=0),"",IF(OR(D29="g",D29="ml"),F29/E29*1000,F29/E29)) | H29: =IF(G29="","",IF(D29="g","o quilo",IF(D29="ml","o litro","a unidade")))
G30: =IF(OR(B30="",E30="",F30="",N(E30)=0),"",IF(OR(D30="g",D30="ml"),F30/E30*1000,F30/E30)) | H30: =IF(G30="","",IF(D30="g","o quilo",IF(D30="ml","o litro","a unidade")))
G31: =IF(OR(B31="",E31="",F31="",N(E31)=0),"",IF(OR(D31="g",D31="ml"),F31/E31*1000,F31/E31)) | H31: =IF(G31="","",IF(D31="g","o quilo",IF(D31="ml","o litro","a unidade")))
G32: =IF(OR(B32="",E32="",F32="",N(E32)=0),"",IF(OR(D32="g",D32="ml"),F32/E32*1000,F32/E32)) | H32: =IF(G32="","",IF(D32="g","o quilo",IF(D32="ml","o litro","a unidade")))
G33: =IF(OR(B33="",E33="",F33="",N(E33)=0),"",IF(OR(D33="g",D33="ml"),F33/E33*1000,F33/E33)) | H33: =IF(G33="","",IF(D33="g","o quilo",IF(D33="ml","o litro","a unidade")))
G34: =IF(OR(B34="",E34="",F34="",N(E34)=0),"",IF(OR(D34="g",D34="ml"),F34/E34*1000,F34/E34)) | H34: =IF(G34="","",IF(D34="g","o quilo",IF(D34="ml","o litro","a unidade")))
G35: =IF(OR(B35="",E35="",F35="",N(E35)=0),"",IF(OR(D35="g",D35="ml"),F35/E35*1000,F35/E35)) | H35: =IF(G35="","",IF(D35="g","o quilo",IF(D35="ml","o litro","a unidade")))
G36: =IF(OR(B36="",E36="",F36="",N(E36)=0),"",IF(OR(D36="g",D36="ml"),F36/E36*1000,F36/E36)) | H36: =IF(G36="","",IF(D36="g","o quilo",IF(D36="ml","o litro","a unidade")))
G37: =IF(OR(B37="",E37="",F37="",N(E37)=0),"",IF(OR(D37="g",D37="ml"),F37/E37*1000,F37/E37)) | H37: =IF(G37="","",IF(D37="g","o quilo",IF(D37="ml","o litro","a unidade")))
... G204: =IF(OR(B204="",E204="",F204="",N(E204)=0),"",IF(OR(D204="g",D204="ml"),F204/E204*1000,F204/E204)) | H204: =IF(G204="","",IF(D204="g","o quilo",IF(D204="ml","o litro","a unidade")))

Sheet Meu Mês
B1: Meu Mês
B2: Quanto custa manter o seu negócio e quanto você precisa ganhar. Preencha uma vez e mude quando algo mudar.
B4: 1. Contas fixas do mês (o que você paga todo mês, vendendo ou não)
B5: Conta | C5: Valor por mês | D5: Observação
B6: Gás | C6: 60 | D6: A parte do gás usada no trabalho
B7: Luz | C7: 50 | D7: Só a parte do trabalho (geladeira, forno, freezer), se der para separar
B8: Água | C8: 20
B9: Internet e celular | C9: 40
B10: MEI (DAS) | C10: 82 | D10: Se for MEI, o boleto do mês
B11: Transporte e entregas | C11: 100 | D11: Combustível, ônibus, motoboy
B12: Manutenção de equipamentos | C12: 30 | D12: Guarde um pouco por mês para quando algo quebrar
B13: Material de limpeza | C13: 25
B14: Divulgação | C14: 0 | D14: Cardápio, anúncio, cartão
B15: Mensalidade da maquininha | C15: 0
B16: Aluguel ou ponto (a parte que usa) | C16: 0
B21: Total das contas fixas | C21: =SUM(C6:C20) -> 407 | D21: A planilha soma sozinha.
B23: 2. Você
B24: Quanto preciso para viver por mês (meu salário) | C24: 1500 | D24: O que você quer tirar para você, todo mês, para pagar as suas contas de casa.
B26: 3. Seu tempo
B27: Dias que trabalho no mês | C27: 22 | D27: Contando os dias de comprar, preparar e entregar.
B28: Horas por dia | C28: 5 | D28: Preparando, comprando, atendendo, entregando e cobrando.
B29: Horas no mês | C29: =C27*C28 -> 110
B30: Quanto vale a minha hora | C30: =IF(C29>0,(C21+C24)/C29,0) -> 17.336364 | D30: Contas fixas + seu salário, divididos pelas horas. Entra no preço do que você prepara.
B32: 4. Porcentagens
B33: Taxas sobre a venda | C33: 0.03 | D33: Maquininha, app de entrega. Se só uma parte paga no cartão, use uma média.
B34: Perdas | C34: 0.05 | D34: O que estraga, quebra, vence ou vira brinde.
B35: Lucro que eu quero | C35: 0.15 | D35: Além do seu salário: para guardar, comprar equipamento e crescer.
B37: Resultado
B38: Preciso ganhar por mês (contas + meu salário) | C38: =C21+C24 -> 1907
B39: Para isso, preciso vender por mês mais ou menos | C39: =MetaVendas -> 3069.8333 | D39: Depende dos seus preços. Veja os detalhes no Resumo.
